{
  "generated_at": "2026-03-09T00:27:30.285114Z",
  "source": "coinbase",
  "count": 377,
  "prices": [
    {
      "symbol": "FLUIDUSDT",
      "bid": 2.124,
      "ask": 2.125,
      "source": "coinbase"
    },
    {
      "symbol": "USELESSUSDT",
      "bid": 0.0373,
      "ask": 0.0374,
      "source": "coinbase"
    },
    {
      "symbol": "ALEPHUSDT",
      "bid": 0.0201,
      "ask": 0.0203,
      "source": "coinbase"
    },
    {
      "symbol": "SHPINGUSDT",
      "bid": 0.001321,
      "ask": 0.001337,
      "source": "coinbase"
    },
    {
      "symbol": "FIGHTUSDT",
      "bid": 0.00473,
      "ask": 0.00474,
      "source": "coinbase"
    },
    {
      "symbol": "API3USDT",
      "bid": 0.274,
      "ask": 0.275,
      "source": "coinbase"
    },
    {
      "symbol": "EIGENUSDT",
      "bid": 0.178,
      "ask": 0.179,
      "source": "coinbase"
    },
    {
      "symbol": "ERAUSDT",
      "bid": 0.138,
      "ask": 0.1383,
      "source": "coinbase"
    },
    {
      "symbol": "MOGUSDT",
      "bid": 1.5e-07,
      "ask": 1.6e-07,
      "source": "coinbase"
    },
    {
      "symbol": "ICPUSDT",
      "bid": 2.429,
      "ask": 2.43,
      "source": "coinbase"
    },
    {
      "symbol": "POLUSDT",
      "bid": 0.0957,
      "ask": 0.0959,
      "source": "coinbase"
    },
    {
      "symbol": "MSOLUSDT",
      "bid": 111.21,
      "ask": 111.65,
      "source": "coinbase"
    },
    {
      "symbol": "ZKPUSDT",
      "bid": 0.08293,
      "ask": 0.08307,
      "source": "coinbase"
    },
    {
      "symbol": "SPAUSDT",
      "bid": 0.003416,
      "ask": 0.003421,
      "source": "coinbase"
    },
    {
      "symbol": "GWEIUSDT",
      "bid": 0.046682,
      "ask": 0.046818,
      "source": "coinbase"
    },
    {
      "symbol": "BCHUSDT",
      "bid": 444.11,
      "ask": 444.29,
      "source": "coinbase"
    },
    {
      "symbol": "MNDEUSDT",
      "bid": 0.02167,
      "ask": 0.02176,
      "source": "coinbase"
    },
    {
      "symbol": "CORECHAINUSDT",
      "bid": 0.0785,
      "ask": 0.0788,
      "source": "coinbase"
    },
    {
      "symbol": "RSCUSDT",
      "bid": 0.0844,
      "ask": 0.0848,
      "source": "coinbase"
    },
    {
      "symbol": "APRUSDT",
      "bid": 0.1127,
      "ask": 0.113,
      "source": "coinbase"
    },
    {
      "symbol": "DBRUSDT",
      "bid": 0.01559,
      "ask": 0.0156,
      "source": "coinbase"
    },
    {
      "symbol": "TOSHIUSDT",
      "bid": 0.0002021,
      "ask": 0.0002024,
      "source": "coinbase"
    },
    {
      "symbol": "PUMPUSDT",
      "bid": 0.001925,
      "ask": 0.001926,
      "source": "coinbase"
    },
    {
      "symbol": "BREVUSDT",
      "bid": 0.1365,
      "ask": 0.1367,
      "source": "coinbase"
    },
    {
      "symbol": "BNKRUSDT",
      "bid": 0.0004511,
      "ask": 0.000452,
      "source": "coinbase"
    },
    {
      "symbol": "CRVUSDT",
      "bid": 0.2327,
      "ask": 0.2329,
      "source": "coinbase"
    },
    {
      "symbol": "MINAUSDT",
      "bid": 0.0533,
      "ask": 0.0534,
      "source": "coinbase"
    },
    {
      "symbol": "AMPUSDT",
      "bid": 0.00137,
      "ask": 0.00138,
      "source": "coinbase"
    },
    {
      "symbol": "COTIUSDT",
      "bid": 0.0116,
      "ask": 0.0117,
      "source": "coinbase"
    },
    {
      "symbol": "SDUSDT",
      "bid": 0.1395,
      "ask": 0.1402,
      "source": "coinbase"
    },
    {
      "symbol": "JASMYUSDT",
      "bid": 0.00544,
      "ask": 0.00545,
      "source": "coinbase"
    },
    {
      "symbol": "UMAUSDT",
      "bid": 0.438,
      "ask": 0.442,
      "source": "coinbase"
    },
    {
      "symbol": "BOBAUSDT",
      "bid": 0.0212,
      "ask": 0.0213,
      "source": "coinbase"
    },
    {
      "symbol": "XRPUSDT",
      "bid": 1.3416,
      "ask": 1.3417,
      "source": "coinbase"
    },
    {
      "symbol": "HONEYUSDT",
      "bid": 0.0031,
      "ask": 0.0032,
      "source": "coinbase"
    },
    {
      "symbol": "ENAUSDT",
      "bid": 0.0992,
      "ask": 0.0993,
      "source": "coinbase"
    },
    {
      "symbol": "RAVEUSDT",
      "bid": 0.2556,
      "ask": 0.2564,
      "source": "coinbase"
    },
    {
      "symbol": "TIAUSDT",
      "bid": 0.3123,
      "ask": 0.3125,
      "source": "coinbase"
    },
    {
      "symbol": "PYRUSDT",
      "bid": 0.296,
      "ask": 0.297,
      "source": "coinbase"
    },
    {
      "symbol": "HOMEUSDT",
      "bid": 0.02057,
      "ask": 0.02062,
      "source": "coinbase"
    },
    {
      "symbol": "KAITOUSDT",
      "bid": 0.3631,
      "ask": 0.3638,
      "source": "coinbase"
    },
    {
      "symbol": "CAKEUSDT",
      "bid": 1.301,
      "ask": 1.303,
      "source": "coinbase"
    },
    {
      "symbol": "AVAXUSDT",
      "bid": 8.84,
      "ask": 8.85,
      "source": "coinbase"
    },
    {
      "symbol": "SUSDT",
      "bid": 0.03856,
      "ask": 0.03861,
      "source": "coinbase"
    },
    {
      "symbol": "SKYUSDT",
      "bid": 0.07234,
      "ask": 0.07235,
      "source": "coinbase"
    },
    {
      "symbol": "TROLLUSDT",
      "bid": 0.01339,
      "ask": 0.01344,
      "source": "coinbase"
    },
    {
      "symbol": "HYPERUSDT",
      "bid": 0.0864,
      "ask": 0.0868,
      "source": "coinbase"
    },
    {
      "symbol": "STRKUSDT",
      "bid": 0.038,
      "ask": 0.039,
      "source": "coinbase"
    },
    {
      "symbol": "AGLDUSDT",
      "bid": 0.2609,
      "ask": 0.2617,
      "source": "coinbase"
    },
    {
      "symbol": "ZRXUSDT",
      "bid": 0.101733,
      "ask": 0.101903,
      "source": "coinbase"
    },
    {
      "symbol": "AVTUSDT",
      "bid": 0.62,
      "ask": 0.63,
      "source": "coinbase"
    },
    {
      "symbol": "JITOSOLUSDT",
      "bid": 103.42,
      "ask": 103.51,
      "source": "coinbase"
    },
    {
      "symbol": "HIGHUSDT",
      "bid": 0.133,
      "ask": 0.134,
      "source": "coinbase"
    },
    {
      "symbol": "BIOUSDT",
      "bid": 0.02036,
      "ask": 0.02039,
      "source": "coinbase"
    },
    {
      "symbol": "WCTUSDT",
      "bid": 0.0563,
      "ask": 0.0565,
      "source": "coinbase"
    },
    {
      "symbol": "1INCHUSDT",
      "bid": 0.09,
      "ask": 0.091,
      "source": "coinbase"
    },
    {
      "symbol": "A8USDT",
      "bid": 0.0084,
      "ask": 0.0085,
      "source": "coinbase"
    },
    {
      "symbol": "MATHUSDT",
      "bid": 0.0267,
      "ask": 0.0269,
      "source": "coinbase"
    },
    {
      "symbol": "AIOZUSDT",
      "bid": 0.0637,
      "ask": 0.0638,
      "source": "coinbase"
    },
    {
      "symbol": "XANUSDT",
      "bid": 0.00601,
      "ask": 0.00603,
      "source": "coinbase"
    },
    {
      "symbol": "SUSHIUSDT",
      "bid": 0.1899,
      "ask": 0.1902,
      "source": "coinbase"
    },
    {
      "symbol": "LTCUSDT",
      "bid": 52.72,
      "ask": 52.74,
      "source": "coinbase"
    },
    {
      "symbol": "IPUSDT",
      "bid": 0.775,
      "ask": 0.776,
      "source": "coinbase"
    },
    {
      "symbol": "LSETHUSDT",
      "bid": 2109.03,
      "ask": 2127.36,
      "source": "coinbase"
    },
    {
      "symbol": "HFTUSDT",
      "bid": 0.0149,
      "ask": 0.015,
      "source": "coinbase"
    },
    {
      "symbol": "GSTUSDT",
      "bid": 0.001643,
      "ask": 0.001665,
      "source": "coinbase"
    },
    {
      "symbol": "ARKMUSDT",
      "bid": 0.099,
      "ask": 0.1,
      "source": "coinbase"
    },
    {
      "symbol": "ETCUSDT",
      "bid": 8.0,
      "ask": 8.01,
      "source": "coinbase"
    },
    {
      "symbol": "BNTUSDT",
      "bid": 0.2742,
      "ask": 0.2748,
      "source": "coinbase"
    },
    {
      "symbol": "SEAMUSDT",
      "bid": 0.1087,
      "ask": 0.1088,
      "source": "coinbase"
    },
    {
      "symbol": "ZORAUSDT",
      "bid": 0.01741,
      "ask": 0.01742,
      "source": "coinbase"
    },
    {
      "symbol": "COOKIEUSDT",
      "bid": 0.01926,
      "ask": 0.01929,
      "source": "coinbase"
    },
    {
      "symbol": "ESPUSDT",
      "bid": 0.10556,
      "ask": 0.10568,
      "source": "coinbase"
    },
    {
      "symbol": "STXUSDT",
      "bid": 0.2512,
      "ask": 0.2514,
      "source": "coinbase"
    },
    {
      "symbol": "ENSUSDT",
      "bid": 5.65,
      "ask": 5.67,
      "source": "coinbase"
    },
    {
      "symbol": "ALEOUSDT",
      "bid": 0.0624,
      "ask": 0.0626,
      "source": "coinbase"
    },
    {
      "symbol": "LAUSDT",
      "bid": 0.2159,
      "ask": 0.216,
      "source": "coinbase"
    },
    {
      "symbol": "VVVUSDT",
      "bid": 5.4675,
      "ask": 5.4712,
      "source": "coinbase"
    },
    {
      "symbol": "CVCUSDT",
      "bid": 0.0289,
      "ask": 0.029,
      "source": "coinbase"
    },
    {
      "symbol": "C98USDT",
      "bid": 0.0248,
      "ask": 0.0249,
      "source": "coinbase"
    },
    {
      "symbol": "ALTUSDT",
      "bid": 0.00713,
      "ask": 0.00714,
      "source": "coinbase"
    },
    {
      "symbol": "ACSUSDT",
      "bid": 0.0001751,
      "ask": 0.0001762,
      "source": "coinbase"
    },
    {
      "symbol": "QIUSDT",
      "bid": 0.001809,
      "ask": 0.001814,
      "source": "coinbase"
    },
    {
      "symbol": "PEPEUSDT",
      "bid": 3.2e-06,
      "ask": 3.21e-06,
      "source": "coinbase"
    },
    {
      "symbol": "SWELLUSDT",
      "bid": 0.00117,
      "ask": 0.00118,
      "source": "coinbase"
    },
    {
      "symbol": "LRDSUSDT",
      "bid": 0.0347,
      "ask": 0.035,
      "source": "coinbase"
    },
    {
      "symbol": "GLMUSDT",
      "bid": 0.1222,
      "ask": 0.1226,
      "source": "coinbase"
    },
    {
      "symbol": "B3USDT",
      "bid": 0.000355,
      "ask": 0.000356,
      "source": "coinbase"
    },
    {
      "symbol": "POPCATUSDT",
      "bid": 0.0502,
      "ask": 0.0504,
      "source": "coinbase"
    },
    {
      "symbol": "PONDUSDT",
      "bid": 0.00224,
      "ask": 0.00225,
      "source": "coinbase"
    },
    {
      "symbol": "RADUSDT",
      "bid": 0.228,
      "ask": 0.23,
      "source": "coinbase"
    },
    {
      "symbol": "SHDWUSDT",
      "bid": 0.031,
      "ask": 0.032,
      "source": "coinbase"
    },
    {
      "symbol": "ALICEUSDT",
      "bid": 0.113,
      "ask": 0.115,
      "source": "coinbase"
    },
    {
      "symbol": "ATHUSDT",
      "bid": 0.00589,
      "ask": 0.0059,
      "source": "coinbase"
    },
    {
      "symbol": "XTZUSDT",
      "bid": 0.3594,
      "ask": 0.3597,
      "source": "coinbase"
    },
    {
      "symbol": "FLOWUSDT",
      "bid": 0.039,
      "ask": 0.04,
      "source": "coinbase"
    },
    {
      "symbol": "ELAUSDT",
      "bid": 0.581,
      "ask": 0.586,
      "source": "coinbase"
    },
    {
      "symbol": "CLANKERUSDT",
      "bid": 26.31,
      "ask": 26.38,
      "source": "coinbase"
    },
    {
      "symbol": "VETUSDT",
      "bid": 0.00681,
      "ask": 0.00682,
      "source": "coinbase"
    },
    {
      "symbol": "FORTHUSDT",
      "bid": 0.8536,
      "ask": 0.8551,
      "source": "coinbase"
    },
    {
      "symbol": "CTXUSDT",
      "bid": 0.551,
      "ask": 0.5516,
      "source": "coinbase"
    },
    {
      "symbol": "GRTUSDT",
      "bid": 0.0247,
      "ask": 0.0248,
      "source": "coinbase"
    },
    {
      "symbol": "RONINUSDT",
      "bid": 0.0869,
      "ask": 0.0873,
      "source": "coinbase"
    },
    {
      "symbol": "LRCUSDT",
      "bid": 0.0305,
      "ask": 0.0306,
      "source": "coinbase"
    },
    {
      "symbol": "BONKUSDT",
      "bid": 5.59e-06,
      "ask": 5.6e-06,
      "source": "coinbase"
    },
    {
      "symbol": "CHZUSDT",
      "bid": 0.0363,
      "ask": 0.0364,
      "source": "coinbase"
    },
    {
      "symbol": "FILUSDT",
      "bid": 0.936,
      "ask": 0.937,
      "source": "coinbase"
    },
    {
      "symbol": "TOWNSUSDT",
      "bid": 0.00338,
      "ask": 0.0034,
      "source": "coinbase"
    },
    {
      "symbol": "WUSDT",
      "bid": 0.01766,
      "ask": 0.01767,
      "source": "coinbase"
    },
    {
      "symbol": "MEUSDT",
      "bid": 0.1102,
      "ask": 0.1103,
      "source": "coinbase"
    },
    {
      "symbol": "RSRUSDT",
      "bid": 0.001628,
      "ask": 0.001631,
      "source": "coinbase"
    },
    {
      "symbol": "IMXUSDT",
      "bid": 0.1486,
      "ask": 0.1487,
      "source": "coinbase"
    },
    {
      "symbol": "METISUSDT",
      "bid": 3.1,
      "ask": 3.11,
      "source": "coinbase"
    },
    {
      "symbol": "GMTUSDT",
      "bid": 0.0106,
      "ask": 0.0107,
      "source": "coinbase"
    },
    {
      "symbol": "DIMOUSDT",
      "bid": 0.01248,
      "ask": 0.01249,
      "source": "coinbase"
    },
    {
      "symbol": "FARMUSDT",
      "bid": 12.74,
      "ask": 12.82,
      "source": "coinbase"
    },
    {
      "symbol": "REQUSDT",
      "bid": 0.0615,
      "ask": 0.0617,
      "source": "coinbase"
    },
    {
      "symbol": "PAXUSDT",
      "bid": 0.9987,
      "ask": 0.9997,
      "source": "coinbase"
    },
    {
      "symbol": "LINKUSDT",
      "bid": 8.545,
      "ask": 8.547,
      "source": "coinbase"
    },
    {
      "symbol": "TRACUSDT",
      "bid": 0.3009,
      "ask": 0.302,
      "source": "coinbase"
    },
    {
      "symbol": "AUCTIONUSDT",
      "bid": 4.66,
      "ask": 4.67,
      "source": "coinbase"
    },
    {
      "symbol": "CTSIUSDT",
      "bid": 0.0232,
      "ask": 0.0233,
      "source": "coinbase"
    },
    {
      "symbol": "DRIFTUSDT",
      "bid": 0.078,
      "ask": 0.079,
      "source": "coinbase"
    },
    {
      "symbol": "GFIUSDT",
      "bid": 0.127,
      "ask": 0.1272,
      "source": "coinbase"
    },
    {
      "symbol": "BANDUSDT",
      "bid": 0.208,
      "ask": 0.209,
      "source": "coinbase"
    },
    {
      "symbol": "KRLUSDT",
      "bid": 0.1479,
      "ask": 0.1486,
      "source": "coinbase"
    },
    {
      "symbol": "AWEUSDT",
      "bid": 0.04867,
      "ask": 0.04873,
      "source": "coinbase"
    },
    {
      "symbol": "OPNUSDT",
      "bid": 0.3057,
      "ask": 0.3058,
      "source": "coinbase"
    },
    {
      "symbol": "FOXUSDT",
      "bid": 0.00655,
      "ask": 0.00669,
      "source": "coinbase"
    },
    {
      "symbol": "ACHUSDT",
      "bid": 0.00681,
      "ask": 0.006823,
      "source": "coinbase"
    },
    {
      "symbol": "SWFTCUSDT",
      "bid": 0.003262,
      "ask": 0.003295,
      "source": "coinbase"
    },
    {
      "symbol": "RLCUSDT",
      "bid": 0.3728,
      "ask": 0.3741,
      "source": "coinbase"
    },
    {
      "symbol": "IOUSDT",
      "bid": 0.102,
      "ask": 0.103,
      "source": "coinbase"
    },
    {
      "symbol": "IDEXUSDT",
      "bid": 0.007,
      "ask": 0.0071,
      "source": "coinbase"
    },
    {
      "symbol": "INDEXUSDT",
      "bid": 0.29,
      "ask": 0.3,
      "source": "coinbase"
    },
    {
      "symbol": "GNOUSDT",
      "bid": 122.29,
      "ask": 124.28,
      "source": "coinbase"
    },
    {
      "symbol": "PLUMEUSDT",
      "bid": 0.01366,
      "ask": 0.01369,
      "source": "coinbase"
    },
    {
      "symbol": "VTHOUSDT",
      "bid": 0.000565,
      "ask": 0.000566,
      "source": "coinbase"
    },
    {
      "symbol": "FLOCKUSDT",
      "bid": 0.0544,
      "ask": 0.0545,
      "source": "coinbase"
    },
    {
      "symbol": "ADAUSDT",
      "bid": 0.2501,
      "ask": 0.2502,
      "source": "coinbase"
    },
    {
      "symbol": "RECALLUSDT",
      "bid": 0.0448,
      "ask": 0.0449,
      "source": "coinbase"
    },
    {
      "symbol": "ROSEUSDT",
      "bid": 0.01123,
      "ask": 0.01125,
      "source": "coinbase"
    },
    {
      "symbol": "PYTHUSDT",
      "bid": 0.0459,
      "ask": 0.046,
      "source": "coinbase"
    },
    {
      "symbol": "LPTUSDT",
      "bid": 2.21,
      "ask": 2.22,
      "source": "coinbase"
    },
    {
      "symbol": "SPXUSDT",
      "bid": 0.2986,
      "ask": 0.2988,
      "source": "coinbase"
    },
    {
      "symbol": "PROUSDT",
      "bid": 0.3504,
      "ask": 0.3505,
      "source": "coinbase"
    },
    {
      "symbol": "KEYCATUSDT",
      "bid": 0.000519,
      "ask": 0.000522,
      "source": "coinbase"
    },
    {
      "symbol": "PERPUSDT",
      "bid": 0.0431,
      "ask": 0.0432,
      "source": "coinbase"
    },
    {
      "symbol": "SHIBUSDT",
      "bid": 5.3e-06,
      "ask": 5.31e-06,
      "source": "coinbase"
    },
    {
      "symbol": "GTCUSDT",
      "bid": 0.0786,
      "ask": 0.079,
      "source": "coinbase"
    },
    {
      "symbol": "NMRUSDT",
      "bid": 7.75,
      "ask": 7.76,
      "source": "coinbase"
    },
    {
      "symbol": "BTCUSDT",
      "bid": 66062.97,
      "ask": 66062.98,
      "source": "coinbase"
    },
    {
      "symbol": "BARDUSDT",
      "bid": 1.0702,
      "ask": 1.0722,
      "source": "coinbase"
    },
    {
      "symbol": "RARIUSDT",
      "bid": 0.1466,
      "ask": 0.1467,
      "source": "coinbase"
    },
    {
      "symbol": "00USDT",
      "bid": 0.0045,
      "ask": 0.0046,
      "source": "coinbase"
    },
    {
      "symbol": "LCXUSDT",
      "bid": 0.0432,
      "ask": 0.0439,
      "source": "coinbase"
    },
    {
      "symbol": "AEROUSDT",
      "bid": 0.31715,
      "ask": 0.31732,
      "source": "coinbase"
    },
    {
      "symbol": "AAVEUSDT",
      "bid": 106.08,
      "ask": 106.1,
      "source": "coinbase"
    },
    {
      "symbol": "ILVUSDT",
      "bid": 3.82,
      "ask": 3.83,
      "source": "coinbase"
    },
    {
      "symbol": "MANAUSDT",
      "bid": 0.0894,
      "ask": 0.0895,
      "source": "coinbase"
    },
    {
      "symbol": "FLRUSDT",
      "bid": 0.00883,
      "ask": 0.00885,
      "source": "coinbase"
    },
    {
      "symbol": "NEARUSDT",
      "bid": 1.212,
      "ask": 1.213,
      "source": "coinbase"
    },
    {
      "symbol": "RAREUSDT",
      "bid": 0.0155,
      "ask": 0.0156,
      "source": "coinbase"
    },
    {
      "symbol": "FLOKIUSDT",
      "bid": 2.75e-05,
      "ask": 2.76e-05,
      "source": "coinbase"
    },
    {
      "symbol": "RLSUSDT",
      "bid": 0.00384,
      "ask": 0.00386,
      "source": "coinbase"
    },
    {
      "symbol": "ROBOUSDT",
      "bid": 0.04233,
      "ask": 0.04236,
      "source": "coinbase"
    },
    {
      "symbol": "SUPUSDT",
      "bid": 0.01162,
      "ask": 0.01163,
      "source": "coinbase"
    },
    {
      "symbol": "COWUSDT",
      "bid": 0.2142,
      "ask": 0.2145,
      "source": "coinbase"
    },
    {
      "symbol": "JTOUSDT",
      "bid": 0.2541,
      "ask": 0.2543,
      "source": "coinbase"
    },
    {
      "symbol": "DOODUSDT",
      "bid": 0.002767,
      "ask": 0.00278,
      "source": "coinbase"
    },
    {
      "symbol": "FAIUSDT",
      "bid": 0.00659,
      "ask": 0.0066,
      "source": "coinbase"
    },
    {
      "symbol": "MAGICUSDT",
      "bid": 0.0607,
      "ask": 0.0608,
      "source": "coinbase"
    },
    {
      "symbol": "OPUSDT",
      "bid": 0.115,
      "ask": 0.116,
      "source": "coinbase"
    },
    {
      "symbol": "ETHUSDT",
      "bid": 1937.67,
      "ask": 1937.68,
      "source": "coinbase"
    },
    {
      "symbol": "VARAUSDT",
      "bid": 0.00089,
      "ask": 0.0009,
      "source": "coinbase"
    },
    {
      "symbol": "POLSUSDT",
      "bid": 0.0614,
      "ask": 0.0616,
      "source": "coinbase"
    },
    {
      "symbol": "MAMOUSDT",
      "bid": 0.01355,
      "ask": 0.01365,
      "source": "coinbase"
    },
    {
      "symbol": "PNGUSDT",
      "bid": 0.02483,
      "ask": 0.02533,
      "source": "coinbase"
    },
    {
      "symbol": "RENDERUSDT",
      "bid": 1.362,
      "ask": 1.364,
      "source": "coinbase"
    },
    {
      "symbol": "PROMPTUSDT",
      "bid": 0.04215,
      "ask": 0.04218,
      "source": "coinbase"
    },
    {
      "symbol": "DOGINMEUSDT",
      "bid": 0.0001022,
      "ask": 0.0001033,
      "source": "coinbase"
    },
    {
      "symbol": "KAVAUSDT",
      "bid": 0.0638,
      "ask": 0.0639,
      "source": "coinbase"
    },
    {
      "symbol": "YBUSDT",
      "bid": 0.1574,
      "ask": 0.1578,
      "source": "coinbase"
    },
    {
      "symbol": "DASHUSDT",
      "bid": 30.54,
      "ask": 30.55,
      "source": "coinbase"
    },
    {
      "symbol": "WELLUSDT",
      "bid": 0.004355,
      "ask": 0.004372,
      "source": "coinbase"
    },
    {
      "symbol": "ONDOUSDT",
      "bid": 0.24487,
      "ask": 0.24502,
      "source": "coinbase"
    },
    {
      "symbol": "XPLUSDT",
      "bid": 0.0937,
      "ask": 0.0938,
      "source": "coinbase"
    },
    {
      "symbol": "KERNELUSDT",
      "bid": 0.0795,
      "ask": 0.0798,
      "source": "coinbase"
    },
    {
      "symbol": "GIGAUSDT",
      "bid": 0.00193,
      "ask": 0.00194,
      "source": "coinbase"
    },
    {
      "symbol": "PENDLEUSDT",
      "bid": 1.184,
      "ask": 1.186,
      "source": "coinbase"
    },
    {
      "symbol": "MORPHOUSDT",
      "bid": 1.8559,
      "ask": 1.8606,
      "source": "coinbase"
    },
    {
      "symbol": "WIFUSDT",
      "bid": 0.178,
      "ask": 0.179,
      "source": "coinbase"
    },
    {
      "symbol": "DEXTUSDT",
      "bid": 0.1257,
      "ask": 0.1322,
      "source": "coinbase"
    },
    {
      "symbol": "AVNTUSDT",
      "bid": 0.1504,
      "ask": 0.1506,
      "source": "coinbase"
    },
    {
      "symbol": "FUN1USDT",
      "bid": 0.0354,
      "ask": 0.03544,
      "source": "coinbase"
    },
    {
      "symbol": "ARPAUSDT",
      "bid": 0.0096,
      "ask": 0.0097,
      "source": "coinbase"
    },
    {
      "symbol": "CELRUSDT",
      "bid": 0.00245,
      "ask": 0.00246,
      "source": "coinbase"
    },
    {
      "symbol": "ZROUSDT",
      "bid": 1.982,
      "ask": 1.983,
      "source": "coinbase"
    },
    {
      "symbol": "TAOUSDT",
      "bid": 182.32,
      "ask": 182.36,
      "source": "coinbase"
    },
    {
      "symbol": "ALCXUSDT",
      "bid": 5.94,
      "ask": 5.95,
      "source": "coinbase"
    },
    {
      "symbol": "ASMUSDT",
      "bid": 0.00827,
      "ask": 0.00829,
      "source": "coinbase"
    },
    {
      "symbol": "SPKUSDT",
      "bid": 0.01959,
      "ask": 0.01961,
      "source": "coinbase"
    },
    {
      "symbol": "POWRUSDT",
      "bid": 0.0609,
      "ask": 0.0612,
      "source": "coinbase"
    },
    {
      "symbol": "TRBUSDT",
      "bid": 14.64,
      "ask": 14.66,
      "source": "coinbase"
    },
    {
      "symbol": "BLURUSDT",
      "bid": 0.0187,
      "ask": 0.0188,
      "source": "coinbase"
    },
    {
      "symbol": "PRCLUSDT",
      "bid": 0.0156,
      "ask": 0.0157,
      "source": "coinbase"
    },
    {
      "symbol": "ARBUSDT",
      "bid": 0.0947,
      "ask": 0.0949,
      "source": "coinbase"
    },
    {
      "symbol": "LMTSUSDT",
      "bid": 0.18077,
      "ask": 0.18162,
      "source": "coinbase"
    },
    {
      "symbol": "ZETACHAINUSDT",
      "bid": 0.0496,
      "ask": 0.0498,
      "source": "coinbase"
    },
    {
      "symbol": "SPELLUSDT",
      "bid": 0.0001703,
      "ask": 0.0001706,
      "source": "coinbase"
    },
    {
      "symbol": "HYPEUSDT",
      "bid": 30.86,
      "ask": 30.88,
      "source": "coinbase"
    },
    {
      "symbol": "CVXUSDT",
      "bid": 2.18,
      "ask": 2.184,
      "source": "coinbase"
    },
    {
      "symbol": "BOBBOBUSDT",
      "bid": 0.00596,
      "ask": 0.00598,
      "source": "coinbase"
    },
    {
      "symbol": "VELOUSDT",
      "bid": 0.01571,
      "ask": 0.01577,
      "source": "coinbase"
    },
    {
      "symbol": "ANKRUSDT",
      "bid": 0.00427,
      "ask": 0.00429,
      "source": "coinbase"
    },
    {
      "symbol": "KTAUSDT",
      "bid": 0.2282,
      "ask": 0.2283,
      "source": "coinbase"
    },
    {
      "symbol": "TRUUSDT",
      "bid": 0.0048,
      "ask": 0.0049,
      "source": "coinbase"
    },
    {
      "symbol": "UPUSDT",
      "bid": 0.037,
      "ask": 0.03701,
      "source": "coinbase"
    },
    {
      "symbol": "WLFIUSDT",
      "bid": 0.0971,
      "ask": 0.09718,
      "source": "coinbase"
    },
    {
      "symbol": "BALUSDT",
      "bid": 0.145,
      "ask": 0.1468,
      "source": "coinbase"
    },
    {
      "symbol": "REZUSDT",
      "bid": 0.0032,
      "ask": 0.00321,
      "source": "coinbase"
    },
    {
      "symbol": "HNTUSDT",
      "bid": 1.158,
      "ask": 1.16,
      "source": "coinbase"
    },
    {
      "symbol": "SUPERUSDT",
      "bid": 0.11114,
      "ask": 0.11134,
      "source": "coinbase"
    },
    {
      "symbol": "COSMOSDYDXUSDT",
      "bid": 0.08,
      "ask": 0.0802,
      "source": "coinbase"
    },
    {
      "symbol": "ALGOUSDT",
      "bid": 0.082,
      "ask": 0.0821,
      "source": "coinbase"
    },
    {
      "symbol": "SYRUPUSDT",
      "bid": 0.2183,
      "ask": 0.2184,
      "source": "coinbase"
    },
    {
      "symbol": "ABTUSDT",
      "bid": 0.1652,
      "ask": 0.1676,
      "source": "coinbase"
    },
    {
      "symbol": "BEAMUSDT",
      "bid": 0.001933,
      "ask": 0.001945,
      "source": "coinbase"
    },
    {
      "symbol": "ETHFIUSDT",
      "bid": 0.521,
      "ask": 0.522,
      "source": "coinbase"
    },
    {
      "symbol": "INVUSDT",
      "bid": 17.31,
      "ask": 17.68,
      "source": "coinbase"
    },
    {
      "symbol": "KMNOUSDT",
      "bid": 0.01938,
      "ask": 0.01939,
      "source": "coinbase"
    },
    {
      "symbol": "CROUSDT",
      "bid": 0.07424,
      "ask": 0.07435,
      "source": "coinbase"
    },
    {
      "symbol": "MASKUSDT",
      "bid": 0.42,
      "ask": 0.43,
      "source": "coinbase"
    },
    {
      "symbol": "INJUSDT",
      "bid": 2.807,
      "ask": 2.81,
      "source": "coinbase"
    },
    {
      "symbol": "THQUSDT",
      "bid": 0.02923,
      "ask": 0.02924,
      "source": "coinbase"
    },
    {
      "symbol": "BIGTIMEUSDT",
      "bid": 0.01282,
      "ask": 0.01284,
      "source": "coinbase"
    },
    {
      "symbol": "NOMUSDT",
      "bid": 0.0033,
      "ask": 0.00331,
      "source": "coinbase"
    },
    {
      "symbol": "AERGOUSDT",
      "bid": 0.0531,
      "ask": 0.0532,
      "source": "coinbase"
    },
    {
      "symbol": "DEGENUSDT",
      "bid": 0.000684,
      "ask": 0.000686,
      "source": "coinbase"
    },
    {
      "symbol": "NKNUSDT",
      "bid": 0.0055,
      "ask": 0.0056,
      "source": "coinbase"
    },
    {
      "symbol": "COMPUSDT",
      "bid": 16.7,
      "ask": 16.72,
      "source": "coinbase"
    },
    {
      "symbol": "XLMUSDT",
      "bid": 0.149021,
      "ask": 0.14904,
      "source": "coinbase"
    },
    {
      "symbol": "SXTUSDT",
      "bid": 0.0168,
      "ask": 0.0169,
      "source": "coinbase"
    },
    {
      "symbol": "TUSDT",
      "bid": 0.00648,
      "ask": 0.0065,
      "source": "coinbase"
    },
    {
      "symbol": "USDSUSDT",
      "bid": 0.9997,
      "ask": 0.9999,
      "source": "coinbase"
    },
    {
      "symbol": "LQTYUSDT",
      "bid": 0.2678,
      "ask": 0.2682,
      "source": "coinbase"
    },
    {
      "symbol": "FARTCOINUSDT",
      "bid": 0.1461,
      "ask": 0.1463,
      "source": "coinbase"
    },
    {
      "symbol": "RPLUSDT",
      "bid": 1.82,
      "ask": 1.83,
      "source": "coinbase"
    },
    {
      "symbol": "SUKUUSDT",
      "bid": 0.0073,
      "ask": 0.0074,
      "source": "coinbase"
    },
    {
      "symbol": "BLZUSDT",
      "bid": 0.0124,
      "ask": 0.0125,
      "source": "coinbase"
    },
    {
      "symbol": "TRUSTUSDT",
      "bid": 0.06755,
      "ask": 0.06759,
      "source": "coinbase"
    },
    {
      "symbol": "SEIUSDT",
      "bid": 0.06235,
      "ask": 0.06242,
      "source": "coinbase"
    },
    {
      "symbol": "STGUSDT",
      "bid": 0.1783,
      "ask": 0.1786,
      "source": "coinbase"
    },
    {
      "symbol": "SQDUSDT",
      "bid": 0.0408,
      "ask": 0.0409,
      "source": "coinbase"
    },
    {
      "symbol": "DOTUSDT",
      "bid": 1.457,
      "ask": 1.459,
      "source": "coinbase"
    },
    {
      "symbol": "SAPIENUSDT",
      "bid": 0.07543,
      "ask": 0.07544,
      "source": "coinbase"
    },
    {
      "symbol": "SENTUSDT",
      "bid": 0.02229,
      "ask": 0.02232,
      "source": "coinbase"
    },
    {
      "symbol": "VOXELUSDT",
      "bid": 0.0082,
      "ask": 0.0083,
      "source": "coinbase"
    },
    {
      "symbol": "LAYERUSDT",
      "bid": 0.0784,
      "ask": 0.0787,
      "source": "coinbase"
    },
    {
      "symbol": "OGNUSDT",
      "bid": 0.01892,
      "ask": 0.01897,
      "source": "coinbase"
    },
    {
      "symbol": "SAFEUSDT",
      "bid": 0.0978,
      "ask": 0.0979,
      "source": "coinbase"
    },
    {
      "symbol": "SOLUSDT",
      "bid": 81.93,
      "ask": 81.94,
      "source": "coinbase"
    },
    {
      "symbol": "ASTERUSDT",
      "bid": 0.687,
      "ask": 0.688,
      "source": "coinbase"
    },
    {
      "symbol": "KSMUSDT",
      "bid": 4.46,
      "ask": 4.47,
      "source": "coinbase"
    },
    {
      "symbol": "SYNDUSDT",
      "bid": 0.0476,
      "ask": 0.0478,
      "source": "coinbase"
    },
    {
      "symbol": "WALUSDT",
      "bid": 0.07358,
      "ask": 0.0737,
      "source": "coinbase"
    },
    {
      "symbol": "IOTXUSDT",
      "bid": 0.0133,
      "ask": 0.01343,
      "source": "coinbase"
    },
    {
      "symbol": "NEWTUSDT",
      "bid": 0.0652,
      "ask": 0.0654,
      "source": "coinbase"
    },
    {
      "symbol": "AXLUSDT",
      "bid": 0.0519,
      "ask": 0.0521,
      "source": "coinbase"
    },
    {
      "symbol": "XYOUSDT",
      "bid": 0.00395,
      "ask": 0.00397,
      "source": "coinbase"
    },
    {
      "symbol": "TURBOUSDT",
      "bid": 0.000884,
      "ask": 0.000886,
      "source": "coinbase"
    },
    {
      "symbol": "WLDUSDT",
      "bid": 0.3604,
      "ask": 0.3605,
      "source": "coinbase"
    },
    {
      "symbol": "ZKUSDT",
      "bid": 0.01798,
      "ask": 0.018,
      "source": "coinbase"
    },
    {
      "symbol": "AURORAUSDT",
      "bid": 0.0289,
      "ask": 0.0291,
      "source": "coinbase"
    },
    {
      "symbol": "KITEUSDT",
      "bid": 0.2907,
      "ask": 0.29117,
      "source": "coinbase"
    },
    {
      "symbol": "RNBWUSDT",
      "bid": 0.01846,
      "ask": 0.01856,
      "source": "coinbase"
    },
    {
      "symbol": "GHSTUSDT",
      "bid": 0.083,
      "ask": 0.085,
      "source": "coinbase"
    },
    {
      "symbol": "OCEANUSDT",
      "bid": 0.1102,
      "ask": 0.1111,
      "source": "coinbase"
    },
    {
      "symbol": "QNTUSDT",
      "bid": 62.5,
      "ask": 62.56,
      "source": "coinbase"
    },
    {
      "symbol": "AXSUSDT",
      "bid": 1.115,
      "ask": 1.116,
      "source": "coinbase"
    },
    {
      "symbol": "ASTUSDT",
      "bid": 0.0075,
      "ask": 0.0077,
      "source": "coinbase"
    },
    {
      "symbol": "BATUSDT",
      "bid": 0.09546,
      "ask": 0.09571,
      "source": "coinbase"
    },
    {
      "symbol": "OMNIUSDT",
      "bid": 0.766,
      "ask": 0.777,
      "source": "coinbase"
    },
    {
      "symbol": "PROVEUSDT",
      "bid": 0.2624,
      "ask": 0.2626,
      "source": "coinbase"
    },
    {
      "symbol": "IRYSUSDT",
      "bid": 0.01694,
      "ask": 0.01698,
      "source": "coinbase"
    },
    {
      "symbol": "ZENUSDT",
      "bid": 5.138,
      "ask": 5.144,
      "source": "coinbase"
    },
    {
      "symbol": "CGLDUSDT",
      "bid": 0.0722,
      "ask": 0.0723,
      "source": "coinbase"
    },
    {
      "symbol": "USDTUSDT",
      "bid": 1.0,
      "ask": 1.00003,
      "source": "coinbase"
    },
    {
      "symbol": "TREEUSDT",
      "bid": 0.0663,
      "ask": 0.0665,
      "source": "coinbase"
    },
    {
      "symbol": "PLUUSDT",
      "bid": 0.13996,
      "ask": 0.14281,
      "source": "coinbase"
    },
    {
      "symbol": "HBARUSDT",
      "bid": 0.09408,
      "ask": 0.09409,
      "source": "coinbase"
    },
    {
      "symbol": "ACXUSDT",
      "bid": 0.0326,
      "ask": 0.0327,
      "source": "coinbase"
    },
    {
      "symbol": "DNTUSDT",
      "bid": 0.0072,
      "ask": 0.0073,
      "source": "coinbase"
    },
    {
      "symbol": "SANDUSDT",
      "bid": 0.0778,
      "ask": 0.078,
      "source": "coinbase"
    },
    {
      "symbol": "LIGHTERUSDT",
      "bid": 1.034,
      "ask": 1.035,
      "source": "coinbase"
    },
    {
      "symbol": "DIAUSDT",
      "bid": 0.17834,
      "ask": 0.17893,
      "source": "coinbase"
    },
    {
      "symbol": "IMUUSDT",
      "bid": 0.00277,
      "ask": 0.00278,
      "source": "coinbase"
    },
    {
      "symbol": "SNXUSDT",
      "bid": 0.303,
      "ask": 0.304,
      "source": "coinbase"
    },
    {
      "symbol": "HOPRUSDT",
      "bid": 0.0201,
      "ask": 0.0203,
      "source": "coinbase"
    },
    {
      "symbol": "FETUSDT",
      "bid": 0.1413,
      "ask": 0.1415,
      "source": "coinbase"
    },
    {
      "symbol": "STORJUSDT",
      "bid": 0.0875,
      "ask": 0.0877,
      "source": "coinbase"
    },
    {
      "symbol": "OXTUSDT",
      "bid": 0.0156,
      "ask": 0.0158,
      "source": "coinbase"
    },
    {
      "symbol": "MONUSDT",
      "bid": 0.02052,
      "ask": 0.02053,
      "source": "coinbase"
    },
    {
      "symbol": "SKLUSDT",
      "bid": 0.0065,
      "ask": 0.0066,
      "source": "coinbase"
    },
    {
      "symbol": "TRIAUSDT",
      "bid": 0.022711,
      "ask": 0.022858,
      "source": "coinbase"
    },
    {
      "symbol": "DOGEUSDT",
      "bid": 0.08947,
      "ask": 0.08949,
      "source": "coinbase"
    },
    {
      "symbol": "APEUSDT",
      "bid": 0.093,
      "ask": 0.094,
      "source": "coinbase"
    },
    {
      "symbol": "EGLDUSDT",
      "bid": 4.08,
      "ask": 4.09,
      "source": "coinbase"
    },
    {
      "symbol": "RAYUSDT",
      "bid": 0.5668,
      "ask": 0.5685,
      "source": "coinbase"
    },
    {
      "symbol": "ELSAUSDT",
      "bid": 0.0704,
      "ask": 0.0705,
      "source": "coinbase"
    },
    {
      "symbol": "LDOUSDT",
      "bid": 0.281,
      "ask": 0.282,
      "source": "coinbase"
    },
    {
      "symbol": "SUIUSDT",
      "bid": 0.8839,
      "ask": 0.8841,
      "source": "coinbase"
    },
    {
      "symbol": "OSMOUSDT",
      "bid": 0.0322,
      "ask": 0.0323,
      "source": "coinbase"
    },
    {
      "symbol": "L3USDT",
      "bid": 0.00683,
      "ask": 0.00685,
      "source": "coinbase"
    },
    {
      "symbol": "AKTUSDT",
      "bid": 0.399,
      "ask": 0.4,
      "source": "coinbase"
    },
    {
      "symbol": "PENGUUSDT",
      "bid": 0.006521,
      "ask": 0.006524,
      "source": "coinbase"
    },
    {
      "symbol": "WAXLUSDT",
      "bid": 0.0518,
      "ask": 0.0521,
      "source": "coinbase"
    },
    {
      "symbol": "MOODENGUSDT",
      "bid": 0.0466,
      "ask": 0.0467,
      "source": "coinbase"
    },
    {
      "symbol": "METUSDT",
      "bid": 0.1557,
      "ask": 0.1559,
      "source": "coinbase"
    },
    {
      "symbol": "DOLOUSDT",
      "bid": 0.0323,
      "ask": 0.03242,
      "source": "coinbase"
    },
    {
      "symbol": "MPLXUSDT",
      "bid": 0.0303,
      "ask": 0.0305,
      "source": "coinbase"
    },
    {
      "symbol": "USD1USDT",
      "bid": 0.9997,
      "ask": 0.9998,
      "source": "coinbase"
    },
    {
      "symbol": "BTRSTUSDT",
      "bid": 0.074,
      "ask": 0.076,
      "source": "coinbase"
    },
    {
      "symbol": "MLNUSDT",
      "bid": 3.38,
      "ask": 3.39,
      "source": "coinbase"
    },
    {
      "symbol": "EDGEUSDT",
      "bid": 0.14259,
      "ask": 0.14299,
      "source": "coinbase"
    },
    {
      "symbol": "BERAUSDT",
      "bid": 0.534,
      "ask": 0.536,
      "source": "coinbase"
    },
    {
      "symbol": "CFGUSDT",
      "bid": 0.148,
      "ask": 0.1482,
      "source": "coinbase"
    },
    {
      "symbol": "DEEPUSDT",
      "bid": 0.02852,
      "ask": 0.02854,
      "source": "coinbase"
    },
    {
      "symbol": "WMTXUSDT",
      "bid": 0.06473,
      "ask": 0.06553,
      "source": "coinbase"
    },
    {
      "symbol": "TIMEUSDT",
      "bid": 2.82,
      "ask": 2.93,
      "source": "coinbase"
    },
    {
      "symbol": "TONUSDT",
      "bid": 1.313,
      "ask": 1.314,
      "source": "coinbase"
    },
    {
      "symbol": "GUSDT",
      "bid": 0.00316,
      "ask": 0.00317,
      "source": "coinbase"
    },
    {
      "symbol": "BICOUSDT",
      "bid": 0.0189,
      "ask": 0.0191,
      "source": "coinbase"
    },
    {
      "symbol": "JUPITERUSDT",
      "bid": 0.1644,
      "ask": 0.1646,
      "source": "coinbase"
    },
    {
      "symbol": "TNSRUSDT",
      "bid": 0.044,
      "ask": 0.045,
      "source": "coinbase"
    },
    {
      "symbol": "FIDAUSDT",
      "bid": 0.0147,
      "ask": 0.0148,
      "source": "coinbase"
    },
    {
      "symbol": "NOICEUSDT",
      "bid": 4.77e-05,
      "ask": 4.8e-05,
      "source": "coinbase"
    },
    {
      "symbol": "CBETHUSDT",
      "bid": 2178.27,
      "ask": 2179.79,
      "source": "coinbase"
    },
    {
      "symbol": "AZTECUSDT",
      "bid": 0.02056,
      "ask": 0.02059,
      "source": "coinbase"
    },
    {
      "symbol": "WETUSDT",
      "bid": 0.1057,
      "ask": 0.1058,
      "source": "coinbase"
    },
    {
      "symbol": "PNUTUSDT",
      "bid": 0.0436,
      "ask": 0.0437,
      "source": "coinbase"
    },
    {
      "symbol": "FISUSDT",
      "bid": 0.0168,
      "ask": 0.0169,
      "source": "coinbase"
    },
    {
      "symbol": "DAIUSDT",
      "bid": 0.9999,
      "ask": 1.0,
      "source": "coinbase"
    },
    {
      "symbol": "LINEAUSDT",
      "bid": 0.00307,
      "ask": 0.00308,
      "source": "coinbase"
    },
    {
      "symbol": "ALLOUSDT",
      "bid": 0.1287,
      "ask": 0.129,
      "source": "coinbase"
    },
    {
      "symbol": "INXUSDT",
      "bid": 0.011728,
      "ask": 0.01174,
      "source": "coinbase"
    },
    {
      "symbol": "ZETAUSDT",
      "bid": 0.0496,
      "ask": 0.0497,
      "source": "coinbase"
    },
    {
      "symbol": "XCNUSDT",
      "bid": 0.00468,
      "ask": 0.00469,
      "source": "coinbase"
    },
    {
      "symbol": "ZECUSDT",
      "bid": 198.8,
      "ask": 198.88,
      "source": "coinbase"
    },
    {
      "symbol": "YFIUSDT",
      "bid": 2483.59,
      "ask": 2486.91,
      "source": "coinbase"
    },
    {
      "symbol": "BADGERUSDT",
      "bid": 0.3641,
      "ask": 0.3644,
      "source": "coinbase"
    },
    {
      "symbol": "NEONUSDT",
      "bid": 0.03059,
      "ask": 0.03084,
      "source": "coinbase"
    },
    {
      "symbol": "PUNDIXUSDT",
      "bid": 0.1464,
      "ask": 0.1469,
      "source": "coinbase"
    },
    {
      "symbol": "REDUSDT",
      "bid": 0.1219,
      "ask": 0.1221,
      "source": "coinbase"
    },
    {
      "symbol": "MDTUSDT",
      "bid": 0.00962,
      "ask": 0.00964,
      "source": "coinbase"
    },
    {
      "symbol": "ZKCUSDT",
      "bid": 0.0801,
      "ask": 0.0803,
      "source": "coinbase"
    },
    {
      "symbol": "TRUMPUSDT",
      "bid": 2.97,
      "ask": 2.98,
      "source": "coinbase"
    },
    {
      "symbol": "KARRATUSDT",
      "bid": 0.0053,
      "ask": 0.0054,
      "source": "coinbase"
    },
    {
      "symbol": "NCTUSDT",
      "bid": 0.00639,
      "ask": 0.0064,
      "source": "coinbase"
    },
    {
      "symbol": "ATOMUSDT",
      "bid": 1.738,
      "ask": 1.739,
      "source": "coinbase"
    },
    {
      "symbol": "PAXGUSDT",
      "bid": 5055.67,
      "ask": 5056.04,
      "source": "coinbase"
    },
    {
      "symbol": "SKRUSDT",
      "bid": 0.02397,
      "ask": 0.02403,
      "source": "coinbase"
    },
    {
      "symbol": "UNIUSDT",
      "bid": 3.674,
      "ask": 3.676,
      "source": "coinbase"
    },
    {
      "symbol": "AUDIOUSDT",
      "bid": 0.0205,
      "ask": 0.0206,
      "source": "coinbase"
    },
    {
      "symbol": "ORCAUSDT",
      "bid": 0.8831,
      "ask": 0.8843,
      "source": "coinbase"
    },
    {
      "symbol": "FORTUSDT",
      "bid": 0.0133,
      "ask": 0.0134,
      "source": "coinbase"
    },
    {
      "symbol": "GODSUSDT",
      "bid": 0.03294,
      "ask": 0.03297,
      "source": "coinbase"
    },
    {
      "symbol": "PRIMEUSDT",
      "bid": 0.422,
      "ask": 0.423,
      "source": "coinbase"
    },
    {
      "symbol": "BNBUSDT",
      "bid": 613.18,
      "ask": 613.28,
      "source": "coinbase"
    },
    {
      "symbol": "EULUSDT",
      "bid": 0.912,
      "ask": 0.914,
      "source": "coinbase"
    },
    {
      "symbol": "2ZUSDT",
      "bid": 0.0739,
      "ask": 0.07394,
      "source": "coinbase"
    },
    {
      "symbol": "BIRBUSDT",
      "bid": 0.1367,
      "ask": 0.1369,
      "source": "coinbase"
    },
    {
      "symbol": "PIRATEUSDT",
      "bid": 0.0061,
      "ask": 0.0062,
      "source": "coinbase"
    },
    {
      "symbol": "APTUSDT",
      "bid": 0.935,
      "ask": 0.9354,
      "source": "coinbase"
    },
    {
      "symbol": "BLASTUSDT",
      "bid": 0.00049,
      "ask": 0.0005,
      "source": "coinbase"
    },
    {
      "symbol": "MANTLEUSDT",
      "bid": 0.6491,
      "ask": 0.6497,
      "source": "coinbase"
    },
    {
      "symbol": "KNCUSDT",
      "bid": 0.1246,
      "ask": 0.125,
      "source": "coinbase"
    }
  ]
}