{
  "generated_at": "2026-03-07T23:15:34.478878Z",
  "source": "coinbase",
  "count": 378,
  "prices": [
    {
      "symbol": "FLUIDUSDT",
      "bid": 2.125,
      "ask": 2.128,
      "source": "coinbase"
    },
    {
      "symbol": "API3USDT",
      "bid": 0.274,
      "ask": 0.275,
      "source": "coinbase"
    },
    {
      "symbol": "TOSHIUSDT",
      "bid": 0.0002016,
      "ask": 0.000202,
      "source": "coinbase"
    },
    {
      "symbol": "VTHOUSDT",
      "bid": 0.00057,
      "ask": 0.000572,
      "source": "coinbase"
    },
    {
      "symbol": "SUPERUSDT",
      "bid": 0.11128,
      "ask": 0.11154,
      "source": "coinbase"
    },
    {
      "symbol": "UPUSDT",
      "bid": 0.03763,
      "ask": 0.03781,
      "source": "coinbase"
    },
    {
      "symbol": "ZETAUSDT",
      "bid": 0.0495,
      "ask": 0.0496,
      "source": "coinbase"
    },
    {
      "symbol": "TROLLUSDT",
      "bid": 0.01397,
      "ask": 0.01402,
      "source": "coinbase"
    },
    {
      "symbol": "BNBUSDT",
      "bid": 620.16,
      "ask": 620.23,
      "source": "coinbase"
    },
    {
      "symbol": "RAYUSDT",
      "bid": 0.5771,
      "ask": 0.5783,
      "source": "coinbase"
    },
    {
      "symbol": "SPXUSDT",
      "bid": 0.3086,
      "ask": 0.3089,
      "source": "coinbase"
    },
    {
      "symbol": "MLNUSDT",
      "bid": 3.85,
      "ask": 3.86,
      "source": "coinbase"
    },
    {
      "symbol": "JUPITERUSDT",
      "bid": 0.1704,
      "ask": 0.1707,
      "source": "coinbase"
    },
    {
      "symbol": "HNTUSDT",
      "bid": 1.168,
      "ask": 1.169,
      "source": "coinbase"
    },
    {
      "symbol": "POLSUSDT",
      "bid": 0.0566,
      "ask": 0.0567,
      "source": "coinbase"
    },
    {
      "symbol": "MNDEUSDT",
      "bid": 0.02168,
      "ask": 0.02169,
      "source": "coinbase"
    },
    {
      "symbol": "BNKRUSDT",
      "bid": 0.000481,
      "ask": 0.0004818,
      "source": "coinbase"
    },
    {
      "symbol": "SUIUSDT",
      "bid": 0.8927,
      "ask": 0.8929,
      "source": "coinbase"
    },
    {
      "symbol": "BOBAUSDT",
      "bid": 0.0229,
      "ask": 0.0231,
      "source": "coinbase"
    },
    {
      "symbol": "LQTYUSDT",
      "bid": 0.2723,
      "ask": 0.2728,
      "source": "coinbase"
    },
    {
      "symbol": "BONKUSDT",
      "bid": 5.66e-06,
      "ask": 5.67e-06,
      "source": "coinbase"
    },
    {
      "symbol": "CGLDUSDT",
      "bid": 0.0726,
      "ask": 0.0728,
      "source": "coinbase"
    },
    {
      "symbol": "CBETHUSDT",
      "bid": 2212.76,
      "ask": 2213.98,
      "source": "coinbase"
    },
    {
      "symbol": "AGLDUSDT",
      "bid": 0.265,
      "ask": 0.2656,
      "source": "coinbase"
    },
    {
      "symbol": "SHDWUSDT",
      "bid": 0.032,
      "ask": 0.033,
      "source": "coinbase"
    },
    {
      "symbol": "MSOLUSDT",
      "bid": 112.73,
      "ask": 113.06,
      "source": "coinbase"
    },
    {
      "symbol": "SUPUSDT",
      "bid": 0.01182,
      "ask": 0.01183,
      "source": "coinbase"
    },
    {
      "symbol": "TRUSTUSDT",
      "bid": 0.0683,
      "ask": 0.06834,
      "source": "coinbase"
    },
    {
      "symbol": "ARKMUSDT",
      "bid": 0.1,
      "ask": 0.101,
      "source": "coinbase"
    },
    {
      "symbol": "BARDUSDT",
      "bid": 1.1291,
      "ask": 1.1313,
      "source": "coinbase"
    },
    {
      "symbol": "GTCUSDT",
      "bid": 0.0783,
      "ask": 0.0789,
      "source": "coinbase"
    },
    {
      "symbol": "RSCUSDT",
      "bid": 0.0873,
      "ask": 0.0876,
      "source": "coinbase"
    },
    {
      "symbol": "FARMUSDT",
      "bid": 12.41,
      "ask": 12.5,
      "source": "coinbase"
    },
    {
      "symbol": "FLOCKUSDT",
      "bid": 0.0564,
      "ask": 0.0565,
      "source": "coinbase"
    },
    {
      "symbol": "RADUSDT",
      "bid": 0.233,
      "ask": 0.234,
      "source": "coinbase"
    },
    {
      "symbol": "1INCHUSDT",
      "bid": 0.091,
      "ask": 0.092,
      "source": "coinbase"
    },
    {
      "symbol": "SNXUSDT",
      "bid": 0.308,
      "ask": 0.309,
      "source": "coinbase"
    },
    {
      "symbol": "FOXUSDT",
      "bid": 0.00684,
      "ask": 0.00693,
      "source": "coinbase"
    },
    {
      "symbol": "ELAUSDT",
      "bid": 0.595,
      "ask": 0.6,
      "source": "coinbase"
    },
    {
      "symbol": "ALEOUSDT",
      "bid": 0.0645,
      "ask": 0.0646,
      "source": "coinbase"
    },
    {
      "symbol": "AUCTIONUSDT",
      "bid": 4.7,
      "ask": 4.72,
      "source": "coinbase"
    },
    {
      "symbol": "NEWTUSDT",
      "bid": 0.0645,
      "ask": 0.0646,
      "source": "coinbase"
    },
    {
      "symbol": "SYNDUSDT",
      "bid": 0.059,
      "ask": 0.0591,
      "source": "coinbase"
    },
    {
      "symbol": "ESPUSDT",
      "bid": 0.10764,
      "ask": 0.10798,
      "source": "coinbase"
    },
    {
      "symbol": "POPCATUSDT",
      "bid": 0.049,
      "ask": 0.0491,
      "source": "coinbase"
    },
    {
      "symbol": "NEARUSDT",
      "bid": 1.21,
      "ask": 1.211,
      "source": "coinbase"
    },
    {
      "symbol": "PIRATEUSDT",
      "bid": 0.0063,
      "ask": 0.0064,
      "source": "coinbase"
    },
    {
      "symbol": "SUSHIUSDT",
      "bid": 0.1927,
      "ask": 0.1931,
      "source": "coinbase"
    },
    {
      "symbol": "IRYSUSDT",
      "bid": 0.01766,
      "ask": 0.01767,
      "source": "coinbase"
    },
    {
      "symbol": "EGLDUSDT",
      "bid": 4.04,
      "ask": 4.05,
      "source": "coinbase"
    },
    {
      "symbol": "WAXLUSDT",
      "bid": 0.0529,
      "ask": 0.0535,
      "source": "coinbase"
    },
    {
      "symbol": "AXLUSDT",
      "bid": 0.0529,
      "ask": 0.053,
      "source": "coinbase"
    },
    {
      "symbol": "C98USDT",
      "bid": 0.0246,
      "ask": 0.0248,
      "source": "coinbase"
    },
    {
      "symbol": "WALUSDT",
      "bid": 0.07248,
      "ask": 0.07259,
      "source": "coinbase"
    },
    {
      "symbol": "TRUMPUSDT",
      "bid": 2.99,
      "ask": 3.0,
      "source": "coinbase"
    },
    {
      "symbol": "ALLOUSDT",
      "bid": 0.121,
      "ask": 0.1212,
      "source": "coinbase"
    },
    {
      "symbol": "XRPUSDT",
      "bid": 1.3551,
      "ask": 1.3552,
      "source": "coinbase"
    },
    {
      "symbol": "LINEAUSDT",
      "bid": 0.00307,
      "ask": 0.00308,
      "source": "coinbase"
    },
    {
      "symbol": "BIRBUSDT",
      "bid": 0.1403,
      "ask": 0.1405,
      "source": "coinbase"
    },
    {
      "symbol": "ATOMUSDT",
      "bid": 1.784,
      "ask": 1.786,
      "source": "coinbase"
    },
    {
      "symbol": "IOTXUSDT",
      "bid": 0.01469,
      "ask": 0.01488,
      "source": "coinbase"
    },
    {
      "symbol": "A8USDT",
      "bid": 0.0088,
      "ask": 0.0089,
      "source": "coinbase"
    },
    {
      "symbol": "SPKUSDT",
      "bid": 0.01946,
      "ask": 0.01948,
      "source": "coinbase"
    },
    {
      "symbol": "NCTUSDT",
      "bid": 0.00662,
      "ask": 0.00664,
      "source": "coinbase"
    },
    {
      "symbol": "TIMEUSDT",
      "bid": 2.8,
      "ask": 2.87,
      "source": "coinbase"
    },
    {
      "symbol": "IPUSDT",
      "bid": 0.814,
      "ask": 0.816,
      "source": "coinbase"
    },
    {
      "symbol": "STXUSDT",
      "bid": 0.2553,
      "ask": 0.2555,
      "source": "coinbase"
    },
    {
      "symbol": "MEUSDT",
      "bid": 0.1112,
      "ask": 0.1115,
      "source": "coinbase"
    },
    {
      "symbol": "METISUSDT",
      "bid": 3.23,
      "ask": 3.24,
      "source": "coinbase"
    },
    {
      "symbol": "NKNUSDT",
      "bid": 0.0055,
      "ask": 0.0056,
      "source": "coinbase"
    },
    {
      "symbol": "BLURUSDT",
      "bid": 0.0187,
      "ask": 0.0188,
      "source": "coinbase"
    },
    {
      "symbol": "ABTUSDT",
      "bid": 0.1665,
      "ask": 0.1689,
      "source": "coinbase"
    },
    {
      "symbol": "EDGEUSDT",
      "bid": 0.14217,
      "ask": 0.14258,
      "source": "coinbase"
    },
    {
      "symbol": "DNTUSDT",
      "bid": 0.0073,
      "ask": 0.0074,
      "source": "coinbase"
    },
    {
      "symbol": "BALUSDT",
      "bid": 0.1422,
      "ask": 0.1443,
      "source": "coinbase"
    },
    {
      "symbol": "DIAUSDT",
      "bid": 0.18054,
      "ask": 0.18093,
      "source": "coinbase"
    },
    {
      "symbol": "AMPUSDT",
      "bid": 0.00139,
      "ask": 0.0014,
      "source": "coinbase"
    },
    {
      "symbol": "REQUSDT",
      "bid": 0.0613,
      "ask": 0.0615,
      "source": "coinbase"
    },
    {
      "symbol": "ETCUSDT",
      "bid": 8.11,
      "ask": 8.12,
      "source": "coinbase"
    },
    {
      "symbol": "GSTUSDT",
      "bid": 0.001683,
      "ask": 0.001704,
      "source": "coinbase"
    },
    {
      "symbol": "PLUMEUSDT",
      "bid": 0.01147,
      "ask": 0.01148,
      "source": "coinbase"
    },
    {
      "symbol": "YFIUSDT",
      "bid": 2462.6,
      "ask": 2466.93,
      "source": "coinbase"
    },
    {
      "symbol": "MORPHOUSDT",
      "bid": 1.8142,
      "ask": 1.8205,
      "source": "coinbase"
    },
    {
      "symbol": "WCTUSDT",
      "bid": 0.0575,
      "ask": 0.0577,
      "source": "coinbase"
    },
    {
      "symbol": "SPELLUSDT",
      "bid": 0.0001695,
      "ask": 0.0001698,
      "source": "coinbase"
    },
    {
      "symbol": "HBARUSDT",
      "bid": 0.09554,
      "ask": 0.09555,
      "source": "coinbase"
    },
    {
      "symbol": "PROUSDT",
      "bid": 0.3534,
      "ask": 0.3535,
      "source": "coinbase"
    },
    {
      "symbol": "REZUSDT",
      "bid": 0.00309,
      "ask": 0.0031,
      "source": "coinbase"
    },
    {
      "symbol": "KEYCATUSDT",
      "bid": 0.000527,
      "ask": 0.000533,
      "source": "coinbase"
    },
    {
      "symbol": "CAKEUSDT",
      "bid": 1.314,
      "ask": 1.316,
      "source": "coinbase"
    },
    {
      "symbol": "GWEIUSDT",
      "bid": 0.04649,
      "ask": 0.046606,
      "source": "coinbase"
    },
    {
      "symbol": "OMNIUSDT",
      "bid": 0.771,
      "ask": 0.78,
      "source": "coinbase"
    },
    {
      "symbol": "SHPINGUSDT",
      "bid": 0.001489,
      "ask": 0.001513,
      "source": "coinbase"
    },
    {
      "symbol": "RARIUSDT",
      "bid": 0.1488,
      "ask": 0.1489,
      "source": "coinbase"
    },
    {
      "symbol": "KSMUSDT",
      "bid": 4.39,
      "ask": 4.41,
      "source": "coinbase"
    },
    {
      "symbol": "QIUSDT",
      "bid": 0.001857,
      "ask": 0.001861,
      "source": "coinbase"
    },
    {
      "symbol": "VVVUSDT",
      "bid": 5.8939,
      "ask": 5.8962,
      "source": "coinbase"
    },
    {
      "symbol": "DOGINMEUSDT",
      "bid": 0.0001011,
      "ask": 0.0001016,
      "source": "coinbase"
    },
    {
      "symbol": "SHIBUSDT",
      "bid": 5.31e-06,
      "ask": 5.32e-06,
      "source": "coinbase"
    },
    {
      "symbol": "COOKIEUSDT",
      "bid": 0.01887,
      "ask": 0.01891,
      "source": "coinbase"
    },
    {
      "symbol": "TRBUSDT",
      "bid": 14.51,
      "ask": 14.53,
      "source": "coinbase"
    },
    {
      "symbol": "CORECHAINUSDT",
      "bid": 0.0794,
      "ask": 0.0798,
      "source": "coinbase"
    },
    {
      "symbol": "PRIMEUSDT",
      "bid": 0.425,
      "ask": 0.426,
      "source": "coinbase"
    },
    {
      "symbol": "STRKUSDT",
      "bid": 0.037,
      "ask": 0.038,
      "source": "coinbase"
    },
    {
      "symbol": "LAYERUSDT",
      "bid": 0.081,
      "ask": 0.0813,
      "source": "coinbase"
    },
    {
      "symbol": "FORTHUSDT",
      "bid": 0.8401,
      "ask": 0.8407,
      "source": "coinbase"
    },
    {
      "symbol": "GODSUSDT",
      "bid": 0.03236,
      "ask": 0.0324,
      "source": "coinbase"
    },
    {
      "symbol": "DOGEUSDT",
      "bid": 0.08981,
      "ask": 0.08982,
      "source": "coinbase"
    },
    {
      "symbol": "BEAMUSDT",
      "bid": 0.001982,
      "ask": 0.001993,
      "source": "coinbase"
    },
    {
      "symbol": "XANUSDT",
      "bid": 0.00631,
      "ask": 0.00634,
      "source": "coinbase"
    },
    {
      "symbol": "VARAUSDT",
      "bid": 0.00095,
      "ask": 0.00096,
      "source": "coinbase"
    },
    {
      "symbol": "USD1USDT",
      "bid": 0.9996,
      "ask": 0.9997,
      "source": "coinbase"
    },
    {
      "symbol": "NOICEUSDT",
      "bid": 4.59e-05,
      "ask": 4.62e-05,
      "source": "coinbase"
    },
    {
      "symbol": "CFGUSDT",
      "bid": 0.1483,
      "ask": 0.1488,
      "source": "coinbase"
    },
    {
      "symbol": "YBUSDT",
      "bid": 0.1536,
      "ask": 0.154,
      "source": "coinbase"
    },
    {
      "symbol": "RAVEUSDT",
      "bid": 0.2834,
      "ask": 0.2836,
      "source": "coinbase"
    },
    {
      "symbol": "GLMUSDT",
      "bid": 0.1251,
      "ask": 0.1254,
      "source": "coinbase"
    },
    {
      "symbol": "BNTUSDT",
      "bid": 0.2792,
      "ask": 0.2796,
      "source": "coinbase"
    },
    {
      "symbol": "OCEANUSDT",
      "bid": 0.1035,
      "ask": 0.1042,
      "source": "coinbase"
    },
    {
      "symbol": "INDEXUSDT",
      "bid": 0.29,
      "ask": 0.3,
      "source": "coinbase"
    },
    {
      "symbol": "HOMEUSDT",
      "bid": 0.02407,
      "ask": 0.02412,
      "source": "coinbase"
    },
    {
      "symbol": "ROBOUSDT",
      "bid": 0.03892,
      "ask": 0.03896,
      "source": "coinbase"
    },
    {
      "symbol": "PENDLEUSDT",
      "bid": 1.2,
      "ask": 1.201,
      "source": "coinbase"
    },
    {
      "symbol": "PLUUSDT",
      "bid": 0.14003,
      "ask": 0.14405,
      "source": "coinbase"
    },
    {
      "symbol": "SKLUSDT",
      "bid": 0.0062,
      "ask": 0.0063,
      "source": "coinbase"
    },
    {
      "symbol": "CROUSDT",
      "bid": 0.07455,
      "ask": 0.07464,
      "source": "coinbase"
    },
    {
      "symbol": "TRACUSDT",
      "bid": 0.3045,
      "ask": 0.3057,
      "source": "coinbase"
    },
    {
      "symbol": "FUN1USDT",
      "bid": 0.03624,
      "ask": 0.03629,
      "source": "coinbase"
    },
    {
      "symbol": "ZKPUSDT",
      "bid": 0.08983,
      "ask": 0.08996,
      "source": "coinbase"
    },
    {
      "symbol": "REDUSDT",
      "bid": 0.1269,
      "ask": 0.1271,
      "source": "coinbase"
    },
    {
      "symbol": "LDOUSDT",
      "bid": 0.282,
      "ask": 0.283,
      "source": "coinbase"
    },
    {
      "symbol": "RONINUSDT",
      "bid": 0.0861,
      "ask": 0.0864,
      "source": "coinbase"
    },
    {
      "symbol": "LTCUSDT",
      "bid": 53.4,
      "ask": 53.42,
      "source": "coinbase"
    },
    {
      "symbol": "HONEYUSDT",
      "bid": 0.0031,
      "ask": 0.0032,
      "source": "coinbase"
    },
    {
      "symbol": "DBRUSDT",
      "bid": 0.01609,
      "ask": 0.0161,
      "source": "coinbase"
    },
    {
      "symbol": "BTRSTUSDT",
      "bid": 0.076,
      "ask": 0.078,
      "source": "coinbase"
    },
    {
      "symbol": "AXSUSDT",
      "bid": 1.104,
      "ask": 1.106,
      "source": "coinbase"
    },
    {
      "symbol": "INJUSDT",
      "bid": 2.824,
      "ask": 2.828,
      "source": "coinbase"
    },
    {
      "symbol": "IOUSDT",
      "bid": 0.099,
      "ask": 0.1,
      "source": "coinbase"
    },
    {
      "symbol": "USDTUSDT",
      "bid": 1.00001,
      "ask": 1.00008,
      "source": "coinbase"
    },
    {
      "symbol": "XLMUSDT",
      "bid": 0.149984,
      "ask": 0.150048,
      "source": "coinbase"
    },
    {
      "symbol": "XYOUSDT",
      "bid": 0.004,
      "ask": 0.00402,
      "source": "coinbase"
    },
    {
      "symbol": "BANDUSDT",
      "bid": 0.208,
      "ask": 0.21,
      "source": "coinbase"
    },
    {
      "symbol": "MATHUSDT",
      "bid": 0.0265,
      "ask": 0.0266,
      "source": "coinbase"
    },
    {
      "symbol": "LINKUSDT",
      "bid": 8.687,
      "ask": 8.689,
      "source": "coinbase"
    },
    {
      "symbol": "PRCLUSDT",
      "bid": 0.014,
      "ask": 0.0141,
      "source": "coinbase"
    },
    {
      "symbol": "FILUSDT",
      "bid": 0.948,
      "ask": 0.949,
      "source": "coinbase"
    },
    {
      "symbol": "WUSDT",
      "bid": 0.01763,
      "ask": 0.01765,
      "source": "coinbase"
    },
    {
      "symbol": "BTCUSDT",
      "bid": 67327.99,
      "ask": 67328.0,
      "source": "coinbase"
    },
    {
      "symbol": "PROMPTUSDT",
      "bid": 0.04233,
      "ask": 0.04236,
      "source": "coinbase"
    },
    {
      "symbol": "IDEXUSDT",
      "bid": 0.0067,
      "ask": 0.0068,
      "source": "coinbase"
    },
    {
      "symbol": "SANDUSDT",
      "bid": 0.0786,
      "ask": 0.0788,
      "source": "coinbase"
    },
    {
      "symbol": "KNCUSDT",
      "bid": 0.1256,
      "ask": 0.1259,
      "source": "coinbase"
    },
    {
      "symbol": "QNTUSDT",
      "bid": 64.37,
      "ask": 64.43,
      "source": "coinbase"
    },
    {
      "symbol": "MINAUSDT",
      "bid": 0.0544,
      "ask": 0.0545,
      "source": "coinbase"
    },
    {
      "symbol": "00USDT",
      "bid": 0.0044,
      "ask": 0.0046,
      "source": "coinbase"
    },
    {
      "symbol": "TREEUSDT",
      "bid": 0.0662,
      "ask": 0.0664,
      "source": "coinbase"
    },
    {
      "symbol": "BERAUSDT",
      "bid": 0.538,
      "ask": 0.539,
      "source": "coinbase"
    },
    {
      "symbol": "MDTUSDT",
      "bid": 0.01006,
      "ask": 0.01009,
      "source": "coinbase"
    },
    {
      "symbol": "OPUSDT",
      "bid": 0.115,
      "ask": 0.116,
      "source": "coinbase"
    },
    {
      "symbol": "AWEUSDT",
      "bid": 0.05018,
      "ask": 0.05041,
      "source": "coinbase"
    },
    {
      "symbol": "PENGUUSDT",
      "bid": 0.006554,
      "ask": 0.006555,
      "source": "coinbase"
    },
    {
      "symbol": "ASMUSDT",
      "bid": 0.00684,
      "ask": 0.00685,
      "source": "coinbase"
    },
    {
      "symbol": "DOLOUSDT",
      "bid": 0.03239,
      "ask": 0.03251,
      "source": "coinbase"
    },
    {
      "symbol": "LIGHTERUSDT",
      "bid": 1.127,
      "ask": 1.129,
      "source": "coinbase"
    },
    {
      "symbol": "WLDUSDT",
      "bid": 0.376,
      "ask": 0.3761,
      "source": "coinbase"
    },
    {
      "symbol": "SENTUSDT",
      "bid": 0.0249,
      "ask": 0.02491,
      "source": "coinbase"
    },
    {
      "symbol": "RSRUSDT",
      "bid": 0.001596,
      "ask": 0.0016,
      "source": "coinbase"
    },
    {
      "symbol": "ZKUSDT",
      "bid": 0.01857,
      "ask": 0.0186,
      "source": "coinbase"
    },
    {
      "symbol": "AVAXUSDT",
      "bid": 8.89,
      "ask": 8.9,
      "source": "coinbase"
    },
    {
      "symbol": "PROVEUSDT",
      "bid": 0.2639,
      "ask": 0.2643,
      "source": "coinbase"
    },
    {
      "symbol": "KERNELUSDT",
      "bid": 0.0753,
      "ask": 0.0755,
      "source": "coinbase"
    },
    {
      "symbol": "TRIAUSDT",
      "bid": 0.022783,
      "ask": 0.022943,
      "source": "coinbase"
    },
    {
      "symbol": "NMRUSDT",
      "bid": 8.16,
      "ask": 8.19,
      "source": "coinbase"
    },
    {
      "symbol": "RNBWUSDT",
      "bid": 0.01894,
      "ask": 0.01897,
      "source": "coinbase"
    },
    {
      "symbol": "ETHUSDT",
      "bid": 1968.32,
      "ask": 1968.33,
      "source": "coinbase"
    },
    {
      "symbol": "ZAMAUSDT",
      "bid": 0.01987,
      "ask": 0.01993,
      "source": "coinbase"
    },
    {
      "symbol": "DOTUSDT",
      "bid": 1.441,
      "ask": 1.443,
      "source": "coinbase"
    },
    {
      "symbol": "SAPIENUSDT",
      "bid": 0.07396,
      "ask": 0.07401,
      "source": "coinbase"
    },
    {
      "symbol": "ZRXUSDT",
      "bid": 0.100675,
      "ask": 0.100721,
      "source": "coinbase"
    },
    {
      "symbol": "RLCUSDT",
      "bid": 0.3679,
      "ask": 0.3686,
      "source": "coinbase"
    },
    {
      "symbol": "FETUSDT",
      "bid": 0.1424,
      "ask": 0.1426,
      "source": "coinbase"
    },
    {
      "symbol": "SWFTCUSDT",
      "bid": 0.003354,
      "ask": 0.003379,
      "source": "coinbase"
    },
    {
      "symbol": "WLFIUSDT",
      "bid": 0.09575,
      "ask": 0.09582,
      "source": "coinbase"
    },
    {
      "symbol": "TURBOUSDT",
      "bid": 0.00089,
      "ask": 0.000892,
      "source": "coinbase"
    },
    {
      "symbol": "SDUSDT",
      "bid": 0.1402,
      "ask": 0.1412,
      "source": "coinbase"
    },
    {
      "symbol": "EIGENUSDT",
      "bid": 0.175,
      "ask": 0.177,
      "source": "coinbase"
    },
    {
      "symbol": "KAITOUSDT",
      "bid": 0.3543,
      "ask": 0.3549,
      "source": "coinbase"
    },
    {
      "symbol": "ONDOUSDT",
      "bid": 0.24809,
      "ask": 0.24814,
      "source": "coinbase"
    },
    {
      "symbol": "HYPERUSDT",
      "bid": 0.0889,
      "ask": 0.0892,
      "source": "coinbase"
    },
    {
      "symbol": "SEAMUSDT",
      "bid": 0.109,
      "ask": 0.1091,
      "source": "coinbase"
    },
    {
      "symbol": "TNSRUSDT",
      "bid": 0.044,
      "ask": 0.045,
      "source": "coinbase"
    },
    {
      "symbol": "SKRUSDT",
      "bid": 0.02437,
      "ask": 0.02438,
      "source": "coinbase"
    },
    {
      "symbol": "PNGUSDT",
      "bid": 0.026,
      "ask": 0.02633,
      "source": "coinbase"
    },
    {
      "symbol": "FORTUSDT",
      "bid": 0.0139,
      "ask": 0.014,
      "source": "coinbase"
    },
    {
      "symbol": "ALGOUSDT",
      "bid": 0.0827,
      "ask": 0.0829,
      "source": "coinbase"
    },
    {
      "symbol": "PONDUSDT",
      "bid": 0.00228,
      "ask": 0.00229,
      "source": "coinbase"
    },
    {
      "symbol": "CTXUSDT",
      "bid": 0.5554,
      "ask": 0.5559,
      "source": "coinbase"
    },
    {
      "symbol": "PYRUSDT",
      "bid": 0.292,
      "ask": 0.295,
      "source": "coinbase"
    },
    {
      "symbol": "VETUSDT",
      "bid": 0.00691,
      "ask": 0.00692,
      "source": "coinbase"
    },
    {
      "symbol": "WIFUSDT",
      "bid": 0.177,
      "ask": 0.178,
      "source": "coinbase"
    },
    {
      "symbol": "APTUSDT",
      "bid": 0.9355,
      "ask": 0.9356,
      "source": "coinbase"
    },
    {
      "symbol": "ZORAUSDT",
      "bid": 0.01845,
      "ask": 0.01847,
      "source": "coinbase"
    },
    {
      "symbol": "TONUSDT",
      "bid": 1.322,
      "ask": 1.324,
      "source": "coinbase"
    },
    {
      "symbol": "OPNUSDT",
      "bid": 0.3028,
      "ask": 0.3029,
      "source": "coinbase"
    },
    {
      "symbol": "ATHUSDT",
      "bid": 0.00584,
      "ask": 0.00586,
      "source": "coinbase"
    },
    {
      "symbol": "INVUSDT",
      "bid": 17.75,
      "ask": 17.99,
      "source": "coinbase"
    },
    {
      "symbol": "FAIUSDT",
      "bid": 0.00812,
      "ask": 0.00814,
      "source": "coinbase"
    },
    {
      "symbol": "FLOKIUSDT",
      "bid": 2.76e-05,
      "ask": 2.77e-05,
      "source": "coinbase"
    },
    {
      "symbol": "ROSEUSDT",
      "bid": 0.01144,
      "ask": 0.01146,
      "source": "coinbase"
    },
    {
      "symbol": "GFIUSDT",
      "bid": 0.1314,
      "ask": 0.1315,
      "source": "coinbase"
    },
    {
      "symbol": "B3USDT",
      "bid": 0.000341,
      "ask": 0.000343,
      "source": "coinbase"
    },
    {
      "symbol": "BLASTUSDT",
      "bid": 0.00049,
      "ask": 0.0005,
      "source": "coinbase"
    },
    {
      "symbol": "JASMYUSDT",
      "bid": 0.00536,
      "ask": 0.00538,
      "source": "coinbase"
    },
    {
      "symbol": "EULUSDT",
      "bid": 0.922,
      "ask": 0.924,
      "source": "coinbase"
    },
    {
      "symbol": "SYRUPUSDT",
      "bid": 0.2216,
      "ask": 0.2217,
      "source": "coinbase"
    },
    {
      "symbol": "PUNDIXUSDT",
      "bid": 0.1478,
      "ask": 0.1482,
      "source": "coinbase"
    },
    {
      "symbol": "FIDAUSDT",
      "bid": 0.015,
      "ask": 0.0151,
      "source": "coinbase"
    },
    {
      "symbol": "COMPUSDT",
      "bid": 17.15,
      "ask": 17.19,
      "source": "coinbase"
    },
    {
      "symbol": "JITOSOLUSDT",
      "bid": 105.14,
      "ask": 105.25,
      "source": "coinbase"
    },
    {
      "symbol": "OXTUSDT",
      "bid": 0.0156,
      "ask": 0.0157,
      "source": "coinbase"
    },
    {
      "symbol": "ZENUSDT",
      "bid": 5.357,
      "ask": 5.363,
      "source": "coinbase"
    },
    {
      "symbol": "RECALLUSDT",
      "bid": 0.0453,
      "ask": 0.0454,
      "source": "coinbase"
    },
    {
      "symbol": "USELESSUSDT",
      "bid": 0.0384,
      "ask": 0.0385,
      "source": "coinbase"
    },
    {
      "symbol": "ARPAUSDT",
      "bid": 0.0096,
      "ask": 0.0097,
      "source": "coinbase"
    },
    {
      "symbol": "ASTUSDT",
      "bid": 0.0078,
      "ask": 0.0079,
      "source": "coinbase"
    },
    {
      "symbol": "SWELLUSDT",
      "bid": 0.00118,
      "ask": 0.00119,
      "source": "coinbase"
    },
    {
      "symbol": "IMUUSDT",
      "bid": 0.00287,
      "ask": 0.00288,
      "source": "coinbase"
    },
    {
      "symbol": "VELOUSDT",
      "bid": 0.01596,
      "ask": 0.01604,
      "source": "coinbase"
    },
    {
      "symbol": "XTZUSDT",
      "bid": 0.3611,
      "ask": 0.3614,
      "source": "coinbase"
    },
    {
      "symbol": "CRVUSDT",
      "bid": 0.2326,
      "ask": 0.2328,
      "source": "coinbase"
    },
    {
      "symbol": "PNUTUSDT",
      "bid": 0.044,
      "ask": 0.0441,
      "source": "coinbase"
    },
    {
      "symbol": "DRIFTUSDT",
      "bid": 0.079,
      "ask": 0.08,
      "source": "coinbase"
    },
    {
      "symbol": "CTSIUSDT",
      "bid": 0.0235,
      "ask": 0.0236,
      "source": "coinbase"
    },
    {
      "symbol": "ORCAUSDT",
      "bid": 0.8918,
      "ask": 0.8927,
      "source": "coinbase"
    },
    {
      "symbol": "DEGENUSDT",
      "bid": 0.000675,
      "ask": 0.000677,
      "source": "coinbase"
    },
    {
      "symbol": "ACXUSDT",
      "bid": 0.0325,
      "ask": 0.0326,
      "source": "coinbase"
    },
    {
      "symbol": "DIMOUSDT",
      "bid": 0.0118,
      "ask": 0.01183,
      "source": "coinbase"
    },
    {
      "symbol": "RAREUSDT",
      "bid": 0.0156,
      "ask": 0.0157,
      "source": "coinbase"
    },
    {
      "symbol": "DEXTUSDT",
      "bid": 0.1276,
      "ask": 0.1348,
      "source": "coinbase"
    },
    {
      "symbol": "ENSUSDT",
      "bid": 5.75,
      "ask": 5.76,
      "source": "coinbase"
    },
    {
      "symbol": "COSMOSDYDXUSDT",
      "bid": 0.0803,
      "ask": 0.0805,
      "source": "coinbase"
    },
    {
      "symbol": "SKYUSDT",
      "bid": 0.07172,
      "ask": 0.07173,
      "source": "coinbase"
    },
    {
      "symbol": "DASHUSDT",
      "bid": 31.7,
      "ask": 31.73,
      "source": "coinbase"
    },
    {
      "symbol": "ETHFIUSDT",
      "bid": 0.52,
      "ask": 0.521,
      "source": "coinbase"
    },
    {
      "symbol": "CVXUSDT",
      "bid": 2.162,
      "ask": 2.165,
      "source": "coinbase"
    },
    {
      "symbol": "DEEPUSDT",
      "bid": 0.02758,
      "ask": 0.02761,
      "source": "coinbase"
    },
    {
      "symbol": "L3USDT",
      "bid": 0.00688,
      "ask": 0.0069,
      "source": "coinbase"
    },
    {
      "symbol": "MOGUSDT",
      "bid": 1.5e-07,
      "ask": 1.6e-07,
      "source": "coinbase"
    },
    {
      "symbol": "ACHUSDT",
      "bid": 0.0069,
      "ask": 0.006906,
      "source": "coinbase"
    },
    {
      "symbol": "BCHUSDT",
      "bid": 448.6,
      "ask": 448.62,
      "source": "coinbase"
    },
    {
      "symbol": "ANKRUSDT",
      "bid": 0.00432,
      "ask": 0.00433,
      "source": "coinbase"
    },
    {
      "symbol": "SOLUSDT",
      "bid": 83.16,
      "ask": 83.17,
      "source": "coinbase"
    },
    {
      "symbol": "DOODUSDT",
      "bid": 0.002934,
      "ask": 0.002946,
      "source": "coinbase"
    },
    {
      "symbol": "NOMUSDT",
      "bid": 0.00326,
      "ask": 0.00327,
      "source": "coinbase"
    },
    {
      "symbol": "WETUSDT",
      "bid": 0.1049,
      "ask": 0.1053,
      "source": "coinbase"
    },
    {
      "symbol": "MPLXUSDT",
      "bid": 0.0305,
      "ask": 0.0307,
      "source": "coinbase"
    },
    {
      "symbol": "FLRUSDT",
      "bid": 0.00891,
      "ask": 0.00893,
      "source": "coinbase"
    },
    {
      "symbol": "APRUSDT",
      "bid": 0.1147,
      "ask": 0.1153,
      "source": "coinbase"
    },
    {
      "symbol": "RPLUSDT",
      "bid": 1.78,
      "ask": 1.79,
      "source": "coinbase"
    },
    {
      "symbol": "ALCXUSDT",
      "bid": 6.92,
      "ask": 6.94,
      "source": "coinbase"
    },
    {
      "symbol": "BADGERUSDT",
      "bid": 0.3743,
      "ask": 0.3744,
      "source": "coinbase"
    },
    {
      "symbol": "BICOUSDT",
      "bid": 0.0188,
      "ask": 0.019,
      "source": "coinbase"
    },
    {
      "symbol": "MAMOUSDT",
      "bid": 0.01413,
      "ask": 0.01424,
      "source": "coinbase"
    },
    {
      "symbol": "AVTUSDT",
      "bid": 0.63,
      "ask": 0.64,
      "source": "coinbase"
    },
    {
      "symbol": "XCNUSDT",
      "bid": 0.00465,
      "ask": 0.00466,
      "source": "coinbase"
    },
    {
      "symbol": "GUSDT",
      "bid": 0.00324,
      "ask": 0.00325,
      "source": "coinbase"
    },
    {
      "symbol": "ACSUSDT",
      "bid": 0.000178,
      "ask": 0.0001789,
      "source": "coinbase"
    },
    {
      "symbol": "KAVAUSDT",
      "bid": 0.0664,
      "ask": 0.0665,
      "source": "coinbase"
    },
    {
      "symbol": "COWUSDT",
      "bid": 0.23,
      "ask": 0.2302,
      "source": "coinbase"
    },
    {
      "symbol": "ALTUSDT",
      "bid": 0.00704,
      "ask": 0.00705,
      "source": "coinbase"
    },
    {
      "symbol": "JTOUSDT",
      "bid": 0.2556,
      "ask": 0.2557,
      "source": "coinbase"
    },
    {
      "symbol": "IMXUSDT",
      "bid": 0.1521,
      "ask": 0.1524,
      "source": "coinbase"
    },
    {
      "symbol": "GMTUSDT",
      "bid": 0.0107,
      "ask": 0.0108,
      "source": "coinbase"
    },
    {
      "symbol": "CLANKERUSDT",
      "bid": 26.94,
      "ask": 26.98,
      "source": "coinbase"
    },
    {
      "symbol": "BIOUSDT",
      "bid": 0.02086,
      "ask": 0.02088,
      "source": "coinbase"
    },
    {
      "symbol": "MANAUSDT",
      "bid": 0.091,
      "ask": 0.0911,
      "source": "coinbase"
    },
    {
      "symbol": "PYTHUSDT",
      "bid": 0.0461,
      "ask": 0.0463,
      "source": "coinbase"
    },
    {
      "symbol": "METUSDT",
      "bid": 0.1601,
      "ask": 0.1603,
      "source": "coinbase"
    },
    {
      "symbol": "ELSAUSDT",
      "bid": 0.0723,
      "ask": 0.0724,
      "source": "coinbase"
    },
    {
      "symbol": "CVCUSDT",
      "bid": 0.0293,
      "ask": 0.0294,
      "source": "coinbase"
    },
    {
      "symbol": "LAUSDT",
      "bid": 0.2268,
      "ask": 0.2271,
      "source": "coinbase"
    },
    {
      "symbol": "LCXUSDT",
      "bid": 0.0441,
      "ask": 0.0445,
      "source": "coinbase"
    },
    {
      "symbol": "FARTCOINUSDT",
      "bid": 0.1472,
      "ask": 0.1473,
      "source": "coinbase"
    },
    {
      "symbol": "TOWNSUSDT",
      "bid": 0.00327,
      "ask": 0.00329,
      "source": "coinbase"
    },
    {
      "symbol": "KMNOUSDT",
      "bid": 0.0199,
      "ask": 0.01991,
      "source": "coinbase"
    },
    {
      "symbol": "STGUSDT",
      "bid": 0.1705,
      "ask": 0.171,
      "source": "coinbase"
    },
    {
      "symbol": "CELRUSDT",
      "bid": 0.00246,
      "ask": 0.00247,
      "source": "coinbase"
    },
    {
      "symbol": "LPTUSDT",
      "bid": 2.21,
      "ask": 2.22,
      "source": "coinbase"
    },
    {
      "symbol": "ARBUSDT",
      "bid": 0.0963,
      "ask": 0.0965,
      "source": "coinbase"
    },
    {
      "symbol": "COTIUSDT",
      "bid": 0.0116,
      "ask": 0.0117,
      "source": "coinbase"
    },
    {
      "symbol": "CHZUSDT",
      "bid": 0.0342,
      "ask": 0.0344,
      "source": "coinbase"
    },
    {
      "symbol": "BATUSDT",
      "bid": 0.09752,
      "ask": 0.09764,
      "source": "coinbase"
    },
    {
      "symbol": "SUKUUSDT",
      "bid": 0.0073,
      "ask": 0.0074,
      "source": "coinbase"
    },
    {
      "symbol": "MONUSDT",
      "bid": 0.02171,
      "ask": 0.02172,
      "source": "coinbase"
    },
    {
      "symbol": "RLSUSDT",
      "bid": 0.00377,
      "ask": 0.00378,
      "source": "coinbase"
    },
    {
      "symbol": "LSETHUSDT",
      "bid": 2120.68,
      "ask": 2139.19,
      "source": "coinbase"
    },
    {
      "symbol": "LMTSUSDT",
      "bid": 0.185,
      "ask": 0.18546,
      "source": "coinbase"
    },
    {
      "symbol": "TRUUSDT",
      "bid": 0.0047,
      "ask": 0.0048,
      "source": "coinbase"
    },
    {
      "symbol": "PAXUSDT",
      "bid": 0.9987,
      "ask": 0.9997,
      "source": "coinbase"
    },
    {
      "symbol": "PEPEUSDT",
      "bid": 3.23e-06,
      "ask": 3.24e-06,
      "source": "coinbase"
    },
    {
      "symbol": "ENAUSDT",
      "bid": 0.1004,
      "ask": 0.1005,
      "source": "coinbase"
    },
    {
      "symbol": "GHSTUSDT",
      "bid": 0.084,
      "ask": 0.085,
      "source": "coinbase"
    },
    {
      "symbol": "STORJUSDT",
      "bid": 0.0892,
      "ask": 0.0895,
      "source": "coinbase"
    },
    {
      "symbol": "SQDUSDT",
      "bid": 0.0356,
      "ask": 0.0358,
      "source": "coinbase"
    },
    {
      "symbol": "ADAUSDT",
      "bid": 0.254,
      "ask": 0.2542,
      "source": "coinbase"
    },
    {
      "symbol": "LRCUSDT",
      "bid": 0.0306,
      "ask": 0.0307,
      "source": "coinbase"
    },
    {
      "symbol": "WMTXUSDT",
      "bid": 0.06562,
      "ask": 0.06613,
      "source": "coinbase"
    },
    {
      "symbol": "BREVUSDT",
      "bid": 0.149,
      "ask": 0.1492,
      "source": "coinbase"
    },
    {
      "symbol": "SPAUSDT",
      "bid": 0.003368,
      "ask": 0.003369,
      "source": "coinbase"
    },
    {
      "symbol": "SAFEUSDT",
      "bid": 0.099,
      "ask": 0.0991,
      "source": "coinbase"
    },
    {
      "symbol": "HIGHUSDT",
      "bid": 0.132,
      "ask": 0.133,
      "source": "coinbase"
    },
    {
      "symbol": "APEUSDT",
      "bid": 0.094,
      "ask": 0.095,
      "source": "coinbase"
    },
    {
      "symbol": "PERPUSDT",
      "bid": 0.0532,
      "ask": 0.0533,
      "source": "coinbase"
    },
    {
      "symbol": "POLUSDT",
      "bid": 0.0943,
      "ask": 0.0945,
      "source": "coinbase"
    },
    {
      "symbol": "ZROUSDT",
      "bid": 1.896,
      "ask": 1.898,
      "source": "coinbase"
    },
    {
      "symbol": "NEONUSDT",
      "bid": 0.03052,
      "ask": 0.03059,
      "source": "coinbase"
    },
    {
      "symbol": "FISUSDT",
      "bid": 0.017,
      "ask": 0.0172,
      "source": "coinbase"
    },
    {
      "symbol": "MOODENGUSDT",
      "bid": 0.0466,
      "ask": 0.0468,
      "source": "coinbase"
    },
    {
      "symbol": "ILVUSDT",
      "bid": 3.47,
      "ask": 3.48,
      "source": "coinbase"
    },
    {
      "symbol": "WELLUSDT",
      "bid": 0.004377,
      "ask": 0.004402,
      "source": "coinbase"
    },
    {
      "symbol": "OSMOUSDT",
      "bid": 0.0329,
      "ask": 0.0331,
      "source": "coinbase"
    },
    {
      "symbol": "BIGTIMEUSDT",
      "bid": 0.01294,
      "ask": 0.01297,
      "source": "coinbase"
    },
    {
      "symbol": "MAGICUSDT",
      "bid": 0.0597,
      "ask": 0.0598,
      "source": "coinbase"
    },
    {
      "symbol": "THQUSDT",
      "bid": 0.0301,
      "ask": 0.03013,
      "source": "coinbase"
    },
    {
      "symbol": "AEROUSDT",
      "bid": 0.32668,
      "ask": 0.32696,
      "source": "coinbase"
    },
    {
      "symbol": "MANTLEUSDT",
      "bid": 0.6726,
      "ask": 0.6732,
      "source": "coinbase"
    },
    {
      "symbol": "ZKCUSDT",
      "bid": 0.0811,
      "ask": 0.0813,
      "source": "coinbase"
    },
    {
      "symbol": "KITEUSDT",
      "bid": 0.27904,
      "ask": 0.27957,
      "source": "coinbase"
    },
    {
      "symbol": "OGNUSDT",
      "bid": 0.01912,
      "ask": 0.01915,
      "source": "coinbase"
    },
    {
      "symbol": "UNIUSDT",
      "bid": 3.761,
      "ask": 3.762,
      "source": "coinbase"
    },
    {
      "symbol": "ALEPHUSDT",
      "bid": 0.02,
      "ask": 0.0202,
      "source": "coinbase"
    },
    {
      "symbol": "FLOWUSDT",
      "bid": 0.041,
      "ask": 0.043,
      "source": "coinbase"
    },
    {
      "symbol": "POWRUSDT",
      "bid": 0.0609,
      "ask": 0.0611,
      "source": "coinbase"
    },
    {
      "symbol": "KRLUSDT",
      "bid": 0.1504,
      "ask": 0.1509,
      "source": "coinbase"
    },
    {
      "symbol": "ASTERUSDT",
      "bid": 0.692,
      "ask": 0.693,
      "source": "coinbase"
    },
    {
      "symbol": "AIOZUSDT",
      "bid": 0.0649,
      "ask": 0.065,
      "source": "coinbase"
    },
    {
      "symbol": "TIAUSDT",
      "bid": 0.3182,
      "ask": 0.3183,
      "source": "coinbase"
    },
    {
      "symbol": "GNOUSDT",
      "bid": 124.38,
      "ask": 125.08,
      "source": "coinbase"
    },
    {
      "symbol": "KARRATUSDT",
      "bid": 0.0057,
      "ask": 0.0058,
      "source": "coinbase"
    },
    {
      "symbol": "TUSDT",
      "bid": 0.00635,
      "ask": 0.00637,
      "source": "coinbase"
    },
    {
      "symbol": "BOBBOBUSDT",
      "bid": 0.00591,
      "ask": 0.00593,
      "source": "coinbase"
    },
    {
      "symbol": "AUDIOUSDT",
      "bid": 0.0218,
      "ask": 0.022,
      "source": "coinbase"
    },
    {
      "symbol": "SUSDT",
      "bid": 0.03852,
      "ask": 0.03854,
      "source": "coinbase"
    },
    {
      "symbol": "LRDSUSDT",
      "bid": 0.0348,
      "ask": 0.0349,
      "source": "coinbase"
    },
    {
      "symbol": "RENDERUSDT",
      "bid": 1.36,
      "ask": 1.362,
      "source": "coinbase"
    },
    {
      "symbol": "HFTUSDT",
      "bid": 0.015,
      "ask": 0.0151,
      "source": "coinbase"
    },
    {
      "symbol": "AERGOUSDT",
      "bid": 0.0538,
      "ask": 0.054,
      "source": "coinbase"
    },
    {
      "symbol": "ALICEUSDT",
      "bid": 0.115,
      "ask": 0.116,
      "source": "coinbase"
    },
    {
      "symbol": "PUMPUSDT",
      "bid": 0.001876,
      "ask": 0.001877,
      "source": "coinbase"
    },
    {
      "symbol": "SXTUSDT",
      "bid": 0.0174,
      "ask": 0.0175,
      "source": "coinbase"
    },
    {
      "symbol": "HOPRUSDT",
      "bid": 0.0208,
      "ask": 0.021,
      "source": "coinbase"
    },
    {
      "symbol": "XPLUSDT",
      "bid": 0.0951,
      "ask": 0.0952,
      "source": "coinbase"
    },
    {
      "symbol": "FIGHTUSDT",
      "bid": 0.00509,
      "ask": 0.0051,
      "source": "coinbase"
    },
    {
      "symbol": "PAXGUSDT",
      "bid": 5176.67,
      "ask": 5177.24,
      "source": "coinbase"
    },
    {
      "symbol": "ZECUSDT",
      "bid": 195.53,
      "ask": 195.6,
      "source": "coinbase"
    },
    {
      "symbol": "VOXELUSDT",
      "bid": 0.0082,
      "ask": 0.0083,
      "source": "coinbase"
    },
    {
      "symbol": "AAVEUSDT",
      "bid": 108.6,
      "ask": 108.64,
      "source": "coinbase"
    },
    {
      "symbol": "GRTUSDT",
      "bid": 0.025,
      "ask": 0.0251,
      "source": "coinbase"
    },
    {
      "symbol": "USDSUSDT",
      "bid": 0.9999,
      "ask": 1.0001,
      "source": "coinbase"
    },
    {
      "symbol": "ZETACHAINUSDT",
      "bid": 0.0494,
      "ask": 0.0497,
      "source": "coinbase"
    },
    {
      "symbol": "BLZUSDT",
      "bid": 0.0124,
      "ask": 0.0125,
      "source": "coinbase"
    },
    {
      "symbol": "AURORAUSDT",
      "bid": 0.0288,
      "ask": 0.0289,
      "source": "coinbase"
    },
    {
      "symbol": "AZTECUSDT",
      "bid": 0.02162,
      "ask": 0.02166,
      "source": "coinbase"
    },
    {
      "symbol": "AVNTUSDT",
      "bid": 0.1541,
      "ask": 0.1543,
      "source": "coinbase"
    },
    {
      "symbol": "HYPEUSDT",
      "bid": 30.25,
      "ask": 30.26,
      "source": "coinbase"
    },
    {
      "symbol": "2ZUSDT",
      "bid": 0.0738,
      "ask": 0.07387,
      "source": "coinbase"
    },
    {
      "symbol": "KTAUSDT",
      "bid": 0.2335,
      "ask": 0.2338,
      "source": "coinbase"
    },
    {
      "symbol": "ERAUSDT",
      "bid": 0.1398,
      "ask": 0.1402,
      "source": "coinbase"
    },
    {
      "symbol": "TAOUSDT",
      "bid": 173.96,
      "ask": 173.99,
      "source": "coinbase"
    },
    {
      "symbol": "UMAUSDT",
      "bid": 0.405,
      "ask": 0.406,
      "source": "coinbase"
    },
    {
      "symbol": "SEIUSDT",
      "bid": 0.06434,
      "ask": 0.06438,
      "source": "coinbase"
    },
    {
      "symbol": "GIGAUSDT",
      "bid": 0.00196,
      "ask": 0.00197,
      "source": "coinbase"
    },
    {
      "symbol": "DAIUSDT",
      "bid": 0.9999,
      "ask": 1.0001,
      "source": "coinbase"
    },
    {
      "symbol": "AKTUSDT",
      "bid": 0.39,
      "ask": 0.391,
      "source": "coinbase"
    },
    {
      "symbol": "MASKUSDT",
      "bid": 0.42,
      "ask": 0.43,
      "source": "coinbase"
    },
    {
      "symbol": "INXUSDT",
      "bid": 0.011263,
      "ask": 0.011272,
      "source": "coinbase"
    },
    {
      "symbol": "ICPUSDT",
      "bid": 2.45,
      "ask": 2.451,
      "source": "coinbase"
    }
  ]
}